Workbook

Sheet Panel
B2: Cronograma de entregables y desembolsos
B3: Convenio de Donación N.° 130P-2025000001 · CARE (Asociación Central Asháninka del Río Ene) y Profonanpe · Proyecto ASL2 · Plazos vigentes de la Adenda N.° 01 (27/04/2026)
B4: ▸ Entregables | D4: ▸ Desembolsos | F4: ▸ Vistas por estado | H4: ▸ Línea de tiempo | J4: ▸ Comparativo | L4: ▸ Paso a paso | N4: ▸ Dudas
B6: Fecha ref. (vacío = hoy) | D6: Fecha usada | F6: Aviso «por vencer» (días) | H6: Filtro de la tabla de productos | K6: Producto a consultar (ficha)
D7: =IF(B7="",TODAY(),B7) -> 46309 | F7: 30 | H7: Todos | K7: Producto 3
B8: Celdas amarillas = editables. Los botones de color abren la lista de cada estado. Registra entregas, revisiones, pagos y rendiciones en las hojas Entregables y Desembolsos.
B10: PRÓXIMO VENCIMIENTO | F10: PRODUCTOS VENCIDOS | I10: PRODUCTOS POR VENCER | L10: PRODUCTOS ENTREGADOS / APROBADOS
B11: =IF('Datos gráficos'!$C$42=0,"Sin pendientes",'Datos gráficos'!$C$42) -> 46374 | F11: ='Datos gráficos'!$C$45 -> 2 | I11: ='Datos gráficos'!$C$46 -> 0 | L11: ='Datos gráficos'!$C$47&" de 5 · "&'Datos gráficos'!$C$48&" aprob." -> 1 de 5 · 0 aprob.
B12: =IF('Datos gráficos'!$C$42=0,"No quedan productos con fecha futura.",'Datos gráficos'!$C$43&": vence en "&'Datos gráficos'!$C$44&" días") -> Producto 3: vence en 65 días | F12: =IF('Datos gráficos'!$C$45>0,"Sin marcar como entregados.","Ninguno para la fecha de referencia.") -> Sin marcar como entregados. | I12: ="En los próximos "&DiasAviso&" días." -> En los próximos 30 días. | L12: ="Avance físico (Adenda): "&TEXT('Datos gráficos'!$C$49*100,"0")&" % · Observados: "&'Datos gráficos'!$C$59 -> Avance físico (Adenda): 30 % · Observados: 0
B14: MONTO DEL CONVENIO A CARE | F14: DESEMBOLSADO | I14: LISTO PARA SOLICITAR | L14: SALDO POR RENDIR
B15: =TotalCARE -> 471250 | F15: ='Datos gráficos'!$C$14 -> 0 | I15: ='Datos gráficos'!$C$15 -> 0 | L15: ='Datos gráficos'!$C$57 -> 0
B16: ="Tope Profonanpe S/ "&FIXED(Parámetros!C10,2)&" con compra directa" -> Tope Profonanpe S/ 511,250.00 con compra directa | F16: =TEXT('Datos gráficos'!$C$50*100,"0")&" % del monto" -> 0 % del monto | I16: ="En conformidad: S/ "&FIXED('Datos gráficos'!$C$17,0)&" · Falta rendir: S/ "&FIXED('Datos gráficos'!$C$16,0) -> En conformidad: S/ 141,375 · Falta rendir: S/ 0 | L16: ="Rendido: S/ "&FIXED('Datos gráficos'!$C$58,2)&" · Dudas abiertas: "&'Datos gráficos'!$C$54 -> Rendido: S/ 0.00 · Dudas abiertas: 7
B18: =IF('Datos gráficos'!$C$45>0,"⚠ "&'Datos gráficos'!$C$45&IF('Datos gráficos'!$C$45=1," producto figura como vencido"," productos figuran como vencidos")&". Si ya se entregaron, marca «Sí» en la hoja Entregables (columna L).",IF('Datos gráficos'!$C$46>0,"⏳ "&'Datos gráficos'!$C$46&" producto(s) por vencer en los próximos "&DiasAviso&" días.","✓ Sin productos vencidos ni por vencer para la fecha de referencia.")) -> ⚠ 2 productos figuran como vencidos. Si ya se entregaron, marca «Sí» en la hoja Entregables (columna L).
B20: Botones de estado · Productos (haz clic para ver la lista)
B21: ="TODOS"&CHAR(10)&5 -> TODOS 5 | D21: ="POR ENTREGAR"&CHAR(10)&'Datos gráficos'!$C$27 -> POR ENTREGAR 2 | F21: ="POR VENCER"&CHAR(10)&'Datos gráficos'!$C$28 -> POR VENCER 0 | H21: ="VENCIDOS"&CHAR(10)&'Datos gráficos'!$C$29 -> VENCIDOS 2 | J21: ="EN REVISIÓN"&CHAR(10)&'Datos gráficos'!$C$30 -> EN REVISIÓN 1 | L21: ="OBSERVADO"&CHAR(10)&'Datos gráficos'!$C$31 -> OBSERVADO 0 | N21: ="APROBADO"&CHAR(10)&'Datos gráficos'!$C$32 -> APROBADO 0
B24: Botones de estado · Desembolsos (haz clic para ver la lista)
B25: ="TODOS"&CHAR(10)&4 -> TODOS 4 | D25: ="DESEMBOLSADO"&CHAR(10)&'Datos gráficos'!$C$35 -> DESEMBOLSADO 0 | F25: ="LISTO PARA SOLICITAR"&CHAR(10)&'Datos gráficos'!$C$36 -> LISTO PARA SOLICITAR 0 | H25: ="FALTA RENDICIÓN"&CHAR(10)&'Datos gráficos'!$C$37 -> FALTA RENDICIÓN 0 | J25: ="EN CONFORMIDAD"&CHAR(10)&'Datos gráficos'!$C$38 -> EN CONFORMIDAD 1 | L25: ="PENDIENTE DE PRODUCTO"&CHAR(10)&'Datos gráficos'!$C$39 -> PENDIENTE DE PRODUCTO 3 | N25: ="RENDICIONES"&CHAR(10)&"S/ "&FIXED('Datos gráficos'!$C$57,0)&" por rendir" -> RENDICIONES S/ 0 por rendir
B28: Avance físico (productos entregados, % Adenda) | G28: ='Datos gráficos'!$C$49 -> 0.3 | H28: ='Datos gráficos'!$C$49 -> 0.3
B29: Ejecución financiera (desembolsado / total) | G29: ='Datos gráficos'!$C$50 -> 0 | H29: ='Datos gráficos'!$C$50 -> 0
B30: Rendición (rendido / desembolsado) | G30: ='Datos gráficos'!$C$51 -> 0 | H30: ='Datos gráficos'!$C$51 -> 0
B31: Tiempo transcurrido del convenio | G31: ='Datos gráficos'!$C$52 -> 0.61629881 | H31: ='Datos gráficos'!$C$52 -> 0.61629881 | M31: ="Faltan "&'Datos gráficos'!$C$53&" días al cierre ("&RIGHT("0"&DAY(Cierre),2)&"/"&RIGHT("0"&MONTH(Cierre),2)&"/"&YEAR(Cierre)&")" -> Faltan 226 días al cierre (28/05/2027)
B33: Línea de tiempo de los productos (plazos de la Adenda N.° 01)
B52: ="Fecha de referencia: "&RIGHT("0"&DAY(FechaRef),2)&"/"&RIGHT("0"&MONTH(FechaRef),2)&"/"&YEAR(FechaRef)&". Detalle semanal con la semana actual marcada en la hoja «Línea de tiempo»." -> Fecha de referencia: 14/10/2026. Detalle semanal con la semana actual marcada en la hoja «Línea de tiempo».
B54: ="Productos · filtro: "&FiltroEstado&" ("&'Datos gráficos'!$C$55&" de 5) — cambia el filtro en la celda H7" -> Productos · filtro: Todos (5 de 5) — cambia el filtro en la celda H7
B55: Producto | D55: Título | G55: Fecha límite | H55: Días restantes | I55: Estado | K55: Situación | O55: Desemb.
B56: =IFERROR(INDEX(Entregables!$D$5:$D$9,MATCH(1,Entregables!$AB$5:$AB$9,0)),"") -> Producto 1 | D56: =IFERROR(INDEX(Entregables!$E$5:$E$9,MATCH(1,Entregables!$AB$5:$AB$9,0)),"") -> Plan de trabajo y cronograma | G56: =IFERROR(INDEX(Entregables!$H$5:$H$9,MATCH(1,Entregables!$AB$5:$AB$9,0)),"") -> 46011 | H56: =IFERROR(INDEX(Entregables!$R$5:$R$9,MATCH(1,Entregables!$AB$5:$AB$9,0)),"") -> -298 | I56: =IFERROR(INDEX(Entregables!$S$5:$S$9,MATCH(1,Entregables!$AB$5:$AB$9,0)),"") -> En revisión | K56: =IFERROR(INDEX(Entregables!$T$5:$T$9,MATCH(1,Entregables!$AB$5:$AB$9,0)),"") -> Presentado el 30/11/2025; espera conformidad UGP/FAO | O56: =IFERROR(INDEX(Entregables!$K$5:$K$9,MATCH(1,Entregables!$AB$5:$AB$9,0)),"") -> D1
B57: =IFERROR(INDEX(Entregables!$D$5:$D$9,MATCH(2,Entregables!$AB$5:$AB$9,0)),"") -> Producto 2 · Parte I | D57: =IFERROR(INDEX(Entregables!$E$5:$E$9,MATCH(2,Entregables!$AB$5:$AB$9,0)),"") -> Plan de capacitación y avances | G57: =IFERROR(INDEX(Entregables!$H$5:$H$9,MATCH(2,Entregables!$AB$5:$AB$9,0)),"") -> 46142 | H57: =IFERROR(INDEX(Entregables!$R$5:$R$9,MATCH(2,Entregables!$AB$5:$AB$9,0)),"") -> -167 | I57: =IFERROR(INDEX(Entregables!$S$5:$S$9,MATCH(2,Entregables!$AB$5:$AB$9,0)),"") -> Vencido | K57: =IFERROR(INDEX(Entregables!$T$5:$T$9,MATCH(2,Entregables!$AB$5:$AB$9,0)),"") -> Venció hace 167 días | O57: =IFERROR(INDEX(Entregables!$K$5:$K$9,MATCH(2,Entregables!$AB$5:$AB$9,0)),"") -> D2
B58: =IFERROR(INDEX(Entregables!$D$5:$D$9,MATCH(3,Entregables!$AB$5:$AB$9,0)),"") -> Producto 2 · Parte II | D58: =IFERROR(INDEX(Entregables!$E$5:$E$9,MATCH(3,Entregables!$AB$5:$AB$9,0)),"") -> Plan de recuperación y fichas | G58: =IFERROR(INDEX(Entregables!$H$5:$H$9,MATCH(3,Entregables!$AB$5:$AB$9,0)),"") -> 46203 | H58: =IFERROR(INDEX(Entregables!$R$5:$R$9,MATCH(3,Entregables!$AB$5:$AB$9,0)),"") -> -106 | I58: =IFERROR(INDEX(Entregables!$S$5:$S$9,MATCH(3,Entregables!$AB$5:$AB$9,0)),"") -> Vencido | K58: =IFERROR(INDEX(Entregables!$T$5:$T$9,MATCH(3,Entregables!$AB$5:$AB$9,0)),"") -> Venció hace 106 días | O58: =IFERROR(INDEX(Entregables!$K$5:$K$9,MATCH(3,Entregables!$AB$5:$AB$9,0)),"") -> D2
B59: =IFERROR(INDEX(Entregables!$D$5:$D$9,MATCH(4,Entregables!$AB$5:$AB$9,0)),"") -> Producto 3 | D59: =IFERROR(INDEX(Entregables!$E$5:$E$9,MATCH(4,Entregables!$AB$5:$AB$9,0)),"") -> Pasantía, plantaciones y planes de vida | G59: =IFERROR(INDEX(Entregables!$H$5:$H$9,MATCH(4,Entregables!$AB$5:$AB$9,0)),"") -> 46374 | H59: =IFERROR(INDEX(Entregables!$R$5:$R$9,MATCH(4,Entregables!$AB$5:$AB$9,0)),"") -> 65 | I59: =IFERROR(INDEX(Entregables!$S$5:$S$9,MATCH(4,Entregables!$AB$5:$AB$9,0)),"") -> Por entregar | K59: =IFERROR(INDEX(Entregables!$T$5:$T$9,MATCH(4,Entregables!$AB$5:$AB$9,0)),"") -> Vence en 65 días | O59: =IFERROR(INDEX(Entregables!$K$5:$K$9,MATCH(4,Entregables!$AB$5:$AB$9,0)),"") -> D3
B60: =IFERROR(INDEX(Entregables!$D$5:$D$9,MATCH(5,Entregables!$AB$5:$AB$9,0)),"") -> Producto 4 | D60: =IFERROR(INDEX(Entregables!$E$5:$E$9,MATCH(5,Entregables!$AB$5:$AB$9,0)),"") -> Informe final y resultados | G60: =IFERROR(INDEX(Entregables!$H$5:$H$9,MATCH(5,Entregables!$AB$5:$AB$9,0)),"") -> 46507 | H60: =IFERROR(INDEX(Entregables!$R$5:$R$9,MATCH(5,Entregables!$AB$5:$AB$9,0)),"") -> 198 | I60: =IFERROR(INDEX(Entregables!$S$5:$S$9,MATCH(5,Entregables!$AB$5:$AB$9,0)),"") -> Por entregar | K60: =IFERROR(INDEX(Entregables!$T$5:$T$9,MATCH(5,Entregables!$AB$5:$AB$9,0)),"") -> Vence en 198 días | O60: =IFERROR(INDEX(Entregables!$K$5:$K$9,MATCH(5,Entregables!$AB$5:$AB$9,0)),"") -> D4
B61: =IF('Datos gráficos'!$C$55=0,"No hay productos en este estado para la fecha de referencia.","")
B63: Desembolsos (cláusula novena) y rendiciones
B64: Desemb. | C64: Monto | E64: Lo habilita | G64: Fecha límite producto | H64: ¿Aprobado? | I64: ¿Rendición previa? | J64: Estado | L64: Siguiente paso | O64: Fecha de pago
B65: =Desembolsos!A5 -> D1 | C65: =Desembolsos!B5 -> 141375 | E65: =Desembolsos!G5 -> Producto 1 | G65: =Desembolsos!I5 -> 46011 | H65: =Desembolsos!L5 -> No | I65: =Desembolsos!N5 -> Sí | J65: =Desembolsos!T5 -> En conformidad | L65: =Desembolsos!U5 -> Conseguir la opinión técnica del Componente 2 y las conformidades del Coordinador y de FAO | O65: =IF(Desembolsos!P5="","",Desembolsos!P5)
B66: =Desembolsos!A6 -> D2 | C66: =Desembolsos!B6 -> 141375 | E66: =Desembolsos!G6 -> Producto 2 (Parte I y Parte II) | G66: =Desembolsos!I6 -> 46203 | H66: =Desembolsos!L6 -> No | I66: =Desembolsos!N6 -> No | J66: =Desembolsos!T6 -> Pendiente de producto | L66: =Desembolsos!U6 -> Presentar Producto 2 (Parte I y Parte II) (vence el 30/06/2026) | O66: =IF(Desembolsos!P6="","",Desembolsos!P6)
B67: =Desembolsos!A7 -> D3 | C67: =Desembolsos!B7 -> 117812 | E67: =Desembolsos!G7 -> Producto 3 | G67: =Desembolsos!I7 -> 46374 | H67: =Desembolsos!L7 -> No | I67: =Desembolsos!N7 -> No | J67: =Desembolsos!T7 -> Pendiente de producto | L67: =Desembolsos!U7 -> Presentar Producto 3 (vence el 18/12/2026) | O67: =IF(Desembolsos!P7="","",Desembolsos!P7)
B68: =Desembolsos!A8 -> D4 | C68: =Desembolsos!B8 -> 70688 | E68: =Desembolsos!G8 -> Producto 4 | G68: =Desembolsos!I8 -> 46507 | H68: =Desembolsos!L8 -> No | I68: =Desembolsos!N8 -> No | J68: =Desembolsos!T8 -> Pendiente de producto | L68: =Desembolsos!U8 -> Presentar Producto 4 (vence el 30/04/2027) | O68: =IF(Desembolsos!P8="","",Desembolsos!P8)
B69: Total | C69: =TotalCARE -> 471250 | E69: Montos y requisitos de la cláusula 9.1. La rendición previa exige el 70 % del pago anterior (y el 100 % del penúltimo).
B71: Indicadores gráficos
B72: Estado del dinero (S/ 471,250) | G72: Monto por desembolso y estado | L72: Productos por estado
B91: ="Ficha del producto: "&ProdSel&" — cámbialo en la celda K7" -> Ficha del producto: Producto 3 — cámbialo en la celda K7
B92: Título | E92: =INDEX(Entregables!$E$5:$E$9,'Datos gráficos'!$C$56) -> Pasantía, plantaciones y planes de vida
B93: Plazo vigente (Adenda) | E93: ="Día "&INDEX(Entregables!$F$5:$F$9,'Datos gráficos'!$C$56)&" desde el inicio: "&RIGHT("0"&DAY(INDEX(Entregables!$H$5:$H$9,'Datos gráficos'!$C$56)),2)&"/"&RIGHT("0"&MONTH(INDEX(Entregables!$H$5:$H$9,'Datos gráficos'!$C$56)),2)&"/"&YEAR(INDEX(Entregables!$H$5:$H$9,'Datos gráficos'!$C$56))&" (ventana del "&RIGHT("0"&DAY(INDEX(Entregables!$G$5:$G$9,'Datos gráficos'!$C$56)),2)&"/"&RIGHT("0"&MONTH(INDEX(Entregables!$G$5:$G$9,'Datos gráficos'!$C$56)),2)&"/"&YEAR(INDEX(Entregables!$G$5:$G$9,'Datos gráficos'!$C$56))&", día "&INDEX(Entregables!$I$5:$I$9,'Datos gráficos'!$C$56)&")" -> Día 428 desde el inicio: 18/12/2026 (ventana del 01/07/2026, día 258)
B94: Plazo original y prórroga | E94: ="Día "&INDEX(Entregables!$V$5:$V$9,'Datos gráficos'!$C$56)&" ("&RIGHT("0"&DAY(INDEX(Entregables!$W$5:$W$9,'Datos gráficos'!$C$56)),2)&"/"&RIGHT("0"&MONTH(INDEX(Entregables!$W$5:$W$9,'Datos gráficos'!$C$56)),2)&"/"&YEAR(INDEX(Entregables!$W$5:$W$9,'Datos gráficos'!$C$56))&"). La Adenda lo amplió "&INDEX(Entregables!$X$5:$X$9,'Datos gráficos'!$C$56)&" días." -> Día 360 (11/10/2026). La Adenda lo amplió 68 días.
B95: Estado | E95: =INDEX(Entregables!$S$5:$S$9,'Datos gráficos'!$C$56) -> Por entregar
B96: Situación | E96: =INDEX(Entregables!$T$5:$T$9,'Datos gráficos'!$C$56) -> Vence en 65 días
B97: Puntualidad de la entrega | E97: =IF(INDEX(Entregables!$U$5:$U$9,'Datos gráficos'!$C$56)="","Aún no entregado",INDEX(Entregables!$U$5:$U$9,'Datos gráficos'!$C$56)) -> Aún no entregado
B98: % de avance (Adenda) | E98: =INDEX(Entregables!$J$5:$J$9,'Datos gráficos'!$C$56) -> 0.2
B99: Desembolso vinculado | E99: =INDEX(Desembolsos!$A$5:$A$8,MATCH(INDEX(Entregables!$K$5:$K$9,'Datos gráficos'!$C$56),Desembolsos!$A$5:$A$8,0))&" · S/ "&FIXED(INDEX(Desembolsos!$B$5:$B$8,MATCH(INDEX(Entregables!$K$5:$K$9,'Datos gráficos'!$C$56),Desembolsos!$A$5:$A$8,0)),2)&" · "&INDEX(Desembolsos!$T$5:$T$8,MATCH(INDEX(Entregables!$K$5:$K$9,'Datos gráficos'!$C$56),Desembolsos!$A$5:$A$8,0))&". "&INDEX(Desembolsos!$U$5:$U$8,MATCH(INDEX(Entregables!$K$5:$K$9,'Datos gráficos'!$C$56),Desembolsos!$A$5:$A$8,0)) -> D3 · S/ 117,812.00 · Pendiente de producto. Presentar Producto 3 (vence el 18/12/2026)
B100: Conformidad de FAO en | E100: =INDEX(Entregables!$Y$5:$Y$9,'Datos gráficos'!$C$56) -> el informe final de implementación de planes de vida
B101: Contenidos ((*) = producto clave) | E101: =INDEX(Entregables!$Z$5:$Z$9,'Datos gráficos'!$C$56) -> • Informe de pasantía en recuperación: aprendizajes, lecciones y hallazgos replicables. • Evaluación temprana de plantaciones según el modelo de recuperación seleccionado y adaptado. • Informe de avances en acciones de recuperación, por comunidad y paisaje. • Informe (final) de implementación de planes de vida, con enfoque de género. (*)
B103: Fuentes: Convenio de Donación N.° 130P-2025000001 (16/10/2025) y Adenda N.° 01 (27/04/2026). Fechas calculadas desde la fecha de inicio en Parámetros. Herramienta de apoyo administrativo; no reemplaza la revisión del área legal.

Sheet Entregables
B1: ← Volver al Panel
B2: Entregables (plazos vigentes de la Adenda N.° 01)
B3: Cláusula sexta modificada por la Adenda N.° 01 (27/04/2026). Días calendario contados desde la fecha de inicio (Parámetros). | L3: ▼ Edita las columnas amarillas (L a Q)
A4: Código | B4: Producto | C4: Parte | D4: Etiqueta | E4: Título | F4: Plazo Adenda (días) | G4: Inicio de ventana | H4: Fecha límite (Adenda) | I4: Día de inicio | J4: % avance (Adenda) | K4: Desembolso | L4: ¿Entregado? | M4: Fecha de entrega real | N4: Revisión UGP / FAO | O4: Fecha de observación | P4: Plazo para subsanar | Q4: Fecha de conformidad | R4: Días restantes | S4: Estado | T4: Situación | U4: Puntualidad | V4: Plazo original (días) | W4: Fecha original | X4: Días de prórroga | Y4: Conformidad FAO en | Z4: Contenidos | AA4: Coincide filtro | AB4: Orden filtro | AC4: Todos | AD4: Por entregar | AE4: Por vencer | AF4: Vencido | AG4: En revisión | AH4: Observado | AI4: Aprobado
A5: P1 | B5: Producto 1 | D5: =B5&IF(C5="",""," · "&C5) -> Producto 1 | E5: Plan de trabajo y cronograma | F5: 65 | G5: =Inicio -> 45946 | H5: =Inicio+F5 -> 46011 | I5: 0 | J5: 0.3 | K5: D1 | L5: Sí | M5: 45991 | N5: En revisión | P5: =IF(O5="","",O5+DiasSubsanar) | R5: =H5-FechaRef -> -298 | S5: =IF(L5="Sí",IF(N5="Conforme","Aprobado",IF(N5="Observado","Observado","En revisión")),IF(R5<0,"Vencido",IF(R5<=DiasAviso,"Por vencer","Por entregar"))) -> En revisión | T5: =IF(S5="Aprobado","Conforme"&IF(Q5<>""," desde el "&RIGHT("0"&DAY(Q5),2)&"/"&RIGHT("0"&MONTH(Q5),2)&"/"&YEAR(Q5),""),IF(S5="Observado",IF(P5="","Observado: registra la fecha de observación",IF(P5>=FechaRef,"Subsanar hasta el "&RIGHT("0"&DAY(P5),2)&"/"&RIGHT("0"&MONTH(P5),2)&"/"&YEAR(P5)&" (faltan "&(P5-FechaRef)&" días)","Plazo para subsanar vencido el "&RIGHT("0"&DAY(P5),2)&"/"&RIGHT("0"&MONTH(P5),2)&"/"&YEAR(P5))),IF(S5="En revisión",IF(M5<>"","Presentado el "&RIGHT("0"&DAY(M5),2)&"/"&RIGHT("0"&MONTH(M5),2)&"/"&YEAR(M5)&"; espera conformidad UGP/FAO","Entregado; espera conformidad UGP/FAO"),IF(R5<0,"Venció hace "&-R5&IF(R5=-1," día"," días"),IF(R5=0,"Vence hoy","Vence en "&R5&IF(R5=1," día"," días")))))) -> Presentado el 30/11/2025; espera conformidad UGP/FAO | U5: =IF(L5<>"Sí","",IF(M5="","Sin fecha registrada",IF(M5<=H5,"A tiempo","Con "&(M5-H5)&" días de retraso"))) -> A tiempo | V5: 15 | W5: =Inicio+V5 -> 45961 | X5: =F5-V5 -> 50 | Y5: el plan de trabajo y la metodología | Z5: • Plan de trabajo detallado (actividades, subactividades, indicadores de avance), metodología y cronograma a 18 meses. (*) | AA5: =OR(FiltroEstado="Todos",S5=FiltroEstado) -> TRUE | AB5: =IF(AA5,COUNTIF($AA$5:AA5,TRUE()),"") -> 1 | AC5: =ROW()-4 -> 1 | AD5: =IF($S5=AD$4,COUNTIF($S$5:$S5,AD$4),"") | AE5: =IF($S5=AE$4,COUNTIF($S$5:$S5,AE$4),"") | AF5: =IF($S5=AF$4,COUNTIF($S$5:$S5,AF$4),"") | AG5: =IF($S5=AG$4,COUNTIF($S$5:$S5,AG$4),"") -> 1 | AH5: =IF($S5=AH$4,COUNTIF($S$5:$S5,AH$4),"") | AI5: =IF($S5=AI$4,COUNTIF($S$5:$S5,AI$4),"")
A6: P2-I | B6: Producto 2 | C6: Parte I | D6: =B6&IF(C6="",""," · "&C6) -> Producto 2 · Parte I | E6: Plan de capacitación y avances | F6: 196 | G6: =H5+1 -> 46012 | H6: =Inicio+F6 -> 46142 | I6: =F5+1 -> 66 | J6: 0.2 | K6: D2 | L6: No | P6: =IF(O6="","",O6+DiasSubsanar) | R6: =H6-FechaRef -> -167 | S6: =IF(L6="Sí",IF(N6="Conforme","Aprobado",IF(N6="Observado","Observado","En revisión")),IF(R6<0,"Vencido",IF(R6<=DiasAviso,"Por vencer","Por entregar"))) -> Vencido | T6: =IF(S6="Aprobado","Conforme"&IF(Q6<>""," desde el "&RIGHT("0"&DAY(Q6),2)&"/"&RIGHT("0"&MONTH(Q6),2)&"/"&YEAR(Q6),""),IF(S6="Observado",IF(P6="","Observado: registra la fecha de observación",IF(P6>=FechaRef,"Subsanar hasta el "&RIGHT("0"&DAY(P6),2)&"/"&RIGHT("0"&MONTH(P6),2)&"/"&YEAR(P6)&" (faltan "&(P6-FechaRef)&" días)","Plazo para subsanar vencido el "&RIGHT("0"&DAY(P6),2)&"/"&RIGHT("0"&MONTH(P6),2)&"/"&YEAR(P6))),IF(S6="En revisión",IF(M6<>"","Presentado el "&RIGHT("0"&DAY(M6),2)&"/"&RIGHT("0"&MONTH(M6),2)&"/"&YEAR(M6)&"; espera conformidad UGP/FAO","Entregado; espera conformidad UGP/FAO"),IF(R6<0,"Venció hace "&-R6&IF(R6=-1," día"," días"),IF(R6=0,"Vence hoy","Vence en "&R6&IF(R6=1," día"," días")))))) -> Venció hace 167 días | U6: =IF(L6<>"Sí","",IF(M6="","Sin fecha registrada",IF(M6<=H6,"A tiempo","Con "&(M6-H6)&" días de retraso"))) | V6: 180 | W6: =Inicio+V6 -> 46126 | X6: =F6-V6 -> 16 | Y6: el plan de fortalecimiento de capacidades | Z6: • Plan de capacitación en recuperación: perfiles, competencias, capacidades e indicadores de logro. (*) • Informe de ejecución de los módulos 1 y 2 del plan de capacitación en recuperación y conectividad «Tsimeeri». • Informe de avances en planes de vida en las 03 CCNN. | AA6: =OR(FiltroEstado="Todos",S6=FiltroEstado) -> TRUE | AB6: =IF(AA6,COUNTIF($AA$5:AA6,TRUE()),"") -> 2 | AC6: =ROW()-4 -> 2 | AD6: =IF($S6=AD$4,COUNTIF($S$5:$S6,AD$4),"") | AE6: =IF($S6=AE$4,COUNTIF($S$5:$S6,AE$4),"") | AF6: =IF($S6=AF$4,COUNTIF($S$5:$S6,AF$4),"") -> 1 | AG6: =IF($S6=AG$4,COUNTIF($S$5:$S6,AG$4),"") | AH6: =IF($S6=AH$4,COUNTIF($S$5:$S6,AH$4),"") | AI6: =IF($S6=AI$4,COUNTIF($S$5:$S6,AI$4),"")
A7: P2-II | B7: Producto 2 | C7: Parte II | D7: =B7&IF(C7="",""," · "&C7) -> Producto 2 · Parte II | E7: Plan de recuperación y fichas | F7: 257 | G7: =H6+1 -> 46143 | H7: =Inicio+F7 -> 46203 | I7: =F6+1 -> 197 | J7: 0.15 | K7: D2 | L7: No | P7: =IF(O7="","",O7+DiasSubsanar) | R7: =H7-FechaRef -> -106 | S7: =IF(L7="Sí",IF(N7="Conforme","Aprobado",IF(N7="Observado","Observado","En revisión")),IF(R7<0,"Vencido",IF(R7<=DiasAviso,"Por vencer","Por entregar"))) -> Vencido | T7: =IF(S7="Aprobado","Conforme"&IF(Q7<>""," desde el "&RIGHT("0"&DAY(Q7),2)&"/"&RIGHT("0"&MONTH(Q7),2)&"/"&YEAR(Q7),""),IF(S7="Observado",IF(P7="","Observado: registra la fecha de observación",IF(P7>=FechaRef,"Subsanar hasta el "&RIGHT("0"&DAY(P7),2)&"/"&RIGHT("0"&MONTH(P7),2)&"/"&YEAR(P7)&" (faltan "&(P7-FechaRef)&" días)","Plazo para subsanar vencido el "&RIGHT("0"&DAY(P7),2)&"/"&RIGHT("0"&MONTH(P7),2)&"/"&YEAR(P7))),IF(S7="En revisión",IF(M7<>"","Presentado el "&RIGHT("0"&DAY(M7),2)&"/"&RIGHT("0"&MONTH(M7),2)&"/"&YEAR(M7)&"; espera conformidad UGP/FAO","Entregado; espera conformidad UGP/FAO"),IF(R7<0,"Venció hace "&-R7&IF(R7=-1," día"," días"),IF(R7=0,"Vence hoy","Vence en "&R7&IF(R7=1," día"," días")))))) -> Venció hace 106 días | U7: =IF(L7<>"Sí","",IF(M7="","Sin fecha registrada",IF(M7<=H7,"A tiempo","Con "&(M7-H7)&" días de retraso"))) | V7: 180 | W7: =Inicio+V7 -> 46126 | X7: =F7-V7 -> 77 | Y7: el plan del piloto de recuperación | Z7: • Plan de recuperación y conectividad consensuado con CCNN y actas de aprobación. (*) • Fichas de caracterización de áreas de recuperación. • Informe de ejecución de los módulos 3 y 4 del plan «Tsimeeri». | AA7: =OR(FiltroEstado="Todos",S7=FiltroEstado) -> TRUE | AB7: =IF(AA7,COUNTIF($AA$5:AA7,TRUE()),"") -> 3 | AC7: =ROW()-4 -> 3 | AD7: =IF($S7=AD$4,COUNTIF($S$5:$S7,AD$4),"") | AE7: =IF($S7=AE$4,COUNTIF($S$5:$S7,AE$4),"") | AF7: =IF($S7=AF$4,COUNTIF($S$5:$S7,AF$4),"") -> 2 | AG7: =IF($S7=AG$4,COUNTIF($S$5:$S7,AG$4),"") | AH7: =IF($S7=AH$4,COUNTIF($S$5:$S7,AH$4),"") | AI7: =IF($S7=AI$4,COUNTIF($S$5:$S7,AI$4),"")
A8: P3 | B8: Producto 3 | D8: =B8&IF(C8="",""," · "&C8) -> Producto 3 | E8: Pasantía, plantaciones y planes de vida | F8: 428 | G8: =H7+1 -> 46204 | H8: =Inicio+F8 -> 46374 | I8: =F7+1 -> 258 | J8: 0.2 | K8: D3 | L8: No | P8: =IF(O8="","",O8+DiasSubsanar) | R8: =H8-FechaRef -> 65 | S8: =IF(L8="Sí",IF(N8="Conforme","Aprobado",IF(N8="Observado","Observado","En revisión")),IF(R8<0,"Vencido",IF(R8<=DiasAviso,"Por vencer","Por entregar"))) -> Por entregar | T8: =IF(S8="Aprobado","Conforme"&IF(Q8<>""," desde el "&RIGHT("0"&DAY(Q8),2)&"/"&RIGHT("0"&MONTH(Q8),2)&"/"&YEAR(Q8),""),IF(S8="Observado",IF(P8="","Observado: registra la fecha de observación",IF(P8>=FechaRef,"Subsanar hasta el "&RIGHT("0"&DAY(P8),2)&"/"&RIGHT("0"&MONTH(P8),2)&"/"&YEAR(P8)&" (faltan "&(P8-FechaRef)&" días)","Plazo para subsanar vencido el "&RIGHT("0"&DAY(P8),2)&"/"&RIGHT("0"&MONTH(P8),2)&"/"&YEAR(P8))),IF(S8="En revisión",IF(M8<>"","Presentado el "&RIGHT("0"&DAY(M8),2)&"/"&RIGHT("0"&MONTH(M8),2)&"/"&YEAR(M8)&"; espera conformidad UGP/FAO","Entregado; espera conformidad UGP/FAO"),IF(R8<0,"Venció hace "&-R8&IF(R8=-1," día"," días"),IF(R8=0,"Vence hoy","Vence en "&R8&IF(R8=1," día"," días")))))) -> Vence en 65 días | U8: =IF(L8<>"Sí","",IF(M8="","Sin fecha registrada",IF(M8<=H8,"A tiempo","Con "&(M8-H8)&" días de retraso"))) | V8: 360 | W8: =Inicio+V8 -> 46306 | X8: =F8-V8 -> 68 | Y8: el informe final de implementación de planes de vida | Z8: • Informe de pasantía en recuperación: aprendizajes, lecciones y hallazgos replicables. • Evaluación temprana de plantaciones según el modelo de recuperación seleccionado y adaptado. • Informe de avances en acciones de recuperación, por comunidad y paisaje. • Informe (final) de implementación de planes de vida, con enfoque de género. (*) | AA8: =OR(FiltroEstado="Todos",S8=FiltroEstado) -> TRUE | AB8: =IF(AA8,COUNTIF($AA$5:AA8,TRUE()),"") -> 4 | AC8: =ROW()-4 -> 4 | AD8: =IF($S8=AD$4,COUNTIF($S$5:$S8,AD$4),"") -> 1 | AE8: =IF($S8=AE$4,COUNTIF($S$5:$S8,AE$4),"") | AF8: =IF($S8=AF$4,COUNTIF($S$5:$S8,AF$4),"") | AG8: =IF($S8=AG$4,COUNTIF($S$5:$S8,AG$4),"") | AH8: =IF($S8=AH$4,COUNTIF($S$5:$S8,AH$4),"") | AI8: =IF($S8=AI$4,COUNTIF($S$5:$S8,AI$4),"")
A9: P4 | B9: Producto 4 | D9: =B9&IF(C9="",""," · "&C9) -> Producto 4 | E9: Informe final y resultados | F9: 561 | G9: =H8+1 -> 46375 | H9: =Inicio+F9 -> 46507 | I9: =F8+1 -> 429 | J9: 0.15 | K9: D4 | L9: No | P9: =IF(O9="","",O9+DiasSubsanar) | R9: =H9-FechaRef -> 198 | S9: =IF(L9="Sí",IF(N9="Conforme","Aprobado",IF(N9="Observado","Observado","En revisión")),IF(R9<0,"Vencido",IF(R9<=DiasAviso,"Por vencer","Por entregar"))) -> Por entregar | T9: =IF(S9="Aprobado","Conforme"&IF(Q9<>""," desde el "&RIGHT("0"&DAY(Q9),2)&"/"&RIGHT("0"&MONTH(Q9),2)&"/"&YEAR(Q9),""),IF(S9="Observado",IF(P9="","Observado: registra la fecha de observación",IF(P9>=FechaRef,"Subsanar hasta el "&RIGHT("0"&DAY(P9),2)&"/"&RIGHT("0"&MONTH(P9),2)&"/"&YEAR(P9)&" (faltan "&(P9-FechaRef)&" días)","Plazo para subsanar vencido el "&RIGHT("0"&DAY(P9),2)&"/"&RIGHT("0"&MONTH(P9),2)&"/"&YEAR(P9))),IF(S9="En revisión",IF(M9<>"","Presentado el "&RIGHT("0"&DAY(M9),2)&"/"&RIGHT("0"&MONTH(M9),2)&"/"&YEAR(M9)&"; espera conformidad UGP/FAO","Entregado; espera conformidad UGP/FAO"),IF(R9<0,"Venció hace "&-R9&IF(R9=-1," día"," días"),IF(R9=0,"Vence hoy","Vence en "&R9&IF(R9=1," día"," días")))))) -> Vence en 198 días | U9: =IF(L9<>"Sí","",IF(M9="","Sin fecha registrada",IF(M9<=H9,"A tiempo","Con "&(M9-H9)&" días de retraso"))) | V9: 540 | W9: =Inicio+V9 -> 46486 | X9: =F9-V9 -> 21 | Y9: el informe final del piloto (2,500 ha) y los resultados de capacitación | Z9: • Informe final de 2,500 hectáreas que iniciaron su proceso de recuperación. (*) • Fichas y matrices de monitoreo de la recuperación, con indicadores verificables. • Reporte de acciones y evidencias de monitoreo. • Evidencias de capacidades en recuperación fortalecidas en 60 líderes indígenas locales. (*) • Informe y evidencias de resultados e impactos de los 03 planes de vida. • Indicadores de resultados e impactos del enfoque de género. | AA9: =OR(FiltroEstado="Todos",S9=FiltroEstado) -> TRUE | AB9: =IF(AA9,COUNTIF($AA$5:AA9,TRUE()),"") -> 5 | AC9: =ROW()-4 -> 5 | AD9: =IF($S9=AD$4,COUNTIF($S$5:$S9,AD$4),"") -> 2 | AE9: =IF($S9=AE$4,COUNTIF($S$5:$S9,AE$4),"") | AF9: =IF($S9=AF$4,COUNTIF($S$5:$S9,AF$4),"") | AG9: =IF($S9=AG$4,COUNTIF($S$5:$S9,AG$4),"") | AH9: =IF($S9=AH$4,COUNTIF($S$5:$S9,AH$4),"") | AI9: =IF($S9=AI$4,COUNTIF($S$5:$S9,AI$4),"")
E10: Total | J10: =SUM(J5:J9) -> 1 | L10: =COUNTIF(L5:L9,"Sí")&" de "&ROWS(L5:L9) -> 1 de 5
A12: (*) Productos clave que requieren conformidad técnica de FAO (cláusula 8.2 y tabla 1 de la Adenda).
A13: Estado: Por entregar → Por vencer (faltan menos días que el aviso) → Vencido (pasó la fecha sin marcar «Sí»). Al marcar «Sí» pasa a En revisión; con la revisión «Observado» u «Conforme» cambia a Observado o Aprobado.
A14: Del Producto 1 solo hay constancia de su presentación el 30/11/2025 (Adenda, punto 1.4). Su conformidad no figura en los documentos: actualiza la columna N cuando la tengas.
A15: Columnas V a X: plazo del convenio original (cláusula 6) y prórroga que otorgó la Adenda. Columnas AA en adelante: auxiliares de los botones y filtros.

Sheet Desembolsos
B1: ← Volver al Panel
B2: Desembolsos y rendiciones (cláusula novena)
B3: Profonanpe transfiere en 4 pagos, previa opinión técnica, conformidades y rendición del pago anterior (cláusulas 9.1, 9.3 y 11.2). | O3: ▼ Edita O, P y Q
A4: N° | B4: Monto (S/) | C4: % del convenio | D4: % cláusula 9.1 | E4: Días según 9.1 | F4: Fecha según 9.1 | G4: Producto(s) que lo habilitan | H4: Código habilitante | I4: Fecha límite del producto (Adenda) | J4: Diferencia (días) | K4: ¿Producto presentado? | L4: ¿Producto aprobado? | M4: Rendición previa requerida | N4: ¿Rendición previa cumplida? | O4: ¿Desembolsado? | P4: Fecha de desembolso | Q4: Monto rendido por CARE (S/) | R4: % rendido | S4: Saldo por rendir (S/) | T4: Estado | U4: Siguiente paso | V4: Desembolsado (S/) | W4: Listo para solicitar (S/) | X4: Falta rendición (S/) | Y4: En conformidad (S/) | Z4: Pendiente de producto (S/) | AA4: Requisitos | AB4: Todos | AC4: Desembolsado | AD4: Listo para solicitar | AE4: Falta rendición | AF4: En conformidad | AG4: Pendiente de producto
A5: D1 | B5: 141375 | C5: =B5/TotalCARE -> 0.3 | D5: 0.3 | E5: 15 | F5: =IF(E5="","Al presentar P4",Inicio+E5) -> 45961 | G5: Producto 1 | H5: P1 | I5: =INDEX(Entregables!$H$5:$H$9,MATCH(H5,Entregables!$A$5:$A$9,0)) -> 46011 | J5: =IF(E5="",0,I5-F5) -> 50 | K5: =IF(Entregables!L5="Sí","Sí","No") -> Sí | L5: =IF(Entregables!S5="Aprobado","Sí","No") -> No | M5: ="No hay rendición previa: es el primer pago." -> No hay rendición previa: es el primer pago. | N5: ="Sí" -> Sí | O5: No | Q5: 0 | R5: =IF(O5="Sí",Q5/B5,"") | S5: =IF(O5="Sí",MAX(0,B5-Q5),0) -> 0 | T5: =IF(O5="Sí","Desembolsado",IF(K5="No","Pendiente de producto",IF(L5="No","En conformidad",IF(N5="Sí","Listo para solicitar","Falta rendición")))) -> En conformidad | U5: =IF(T5="Desembolsado","Pagado"&IF(P5<>""," el "&RIGHT("0"&DAY(P5),2)&"/"&RIGHT("0"&MONTH(P5),2)&"/"&YEAR(P5),"")&IF(S5>0,". Por rendir: S/ "&FIXED(S5,2),". Rendido al 100 %."),IF(T5="Pendiente de producto","Presentar "&G5&" (vence el "&RIGHT("0"&DAY(I5),2)&"/"&RIGHT("0"&MONTH(I5),2)&"/"&YEAR(I5)&")",IF(T5="En conformidad","Conseguir la opinión técnica del Componente 2 y las conformidades del Coordinador y de FAO",IF(T5="Falta rendición",M5,"La UGP debe pedir el desembolso por escrito a Profonanpe (cl. 9.3)")))) -> Conseguir la opinión técnica del Componente 2 y las conformidades del Coordinador y de FAO | V5: =IF($T5="Desembolsado",$B5,0) -> 0 | W5: =IF($T5="Listo para solicitar",$B5,0) -> 0 | X5: =IF($T5="Falta rendición",$B5,0) -> 0 | Y5: =IF($T5="En conformidad",$B5,0) -> 141375 | Z5: =IF($T5="Pendiente de producto",$B5,0) -> 0 | AA5: • Presentar el Producto 1. • Opinión técnica del Componente 2, conformidad del Coordinador Técnico y conformidad técnica de FAO. | AB5: =ROW()-4 -> 1 | AC5: =IF($T5=AC$4,COUNTIF($T$5:$T5,AC$4),"") | AD5: =IF($T5=AD$4,COUNTIF($T$5:$T5,AD$4),"") | AE5: =IF($T5=AE$4,COUNTIF($T$5:$T5,AE$4),"") | AF5: =IF($T5=AF$4,COUNTIF($T$5:$T5,AF$4),"") -> 1 | AG5: =IF($T5=AG$4,COUNTIF($T$5:$T5,AG$4),"")
A6: D2 | B6: 141375 | C6: =B6/TotalCARE -> 0.3 | D6: 0.3 | E6: 120 | F6: =IF(E6="","Al presentar P4",Inicio+E6) -> 46066 | G6: Producto 2 (Parte I y Parte II) | H6: P2-II | I6: =INDEX(Entregables!$H$5:$H$9,MATCH(H6,Entregables!$A$5:$A$9,0)) -> 46203 | J6: =IF(E6="",0,I6-F6) -> 137 | K6: =IF(AND(Entregables!L6="Sí",Entregables!L7="Sí"),"Sí","No") -> No | L6: =IF(AND(Entregables!S6="Aprobado",Entregables!S7="Aprobado"),"Sí","No") -> No | M6: ="Rendir al menos el "&TEXT(Rendicion*100,"0")&" % del 1.er desembolso: S/ "&FIXED(B5*Rendicion,2)&". Informe de recursos financiados." -> Rendir al menos el 70 % del 1.er desembolso: S/ 98,962.50. Informe de recursos financiados. | N6: =IF(Q5>=B5*Rendicion-0.005,"Sí","No") -> No | O6: No | Q6: 0 | R6: =IF(O6="Sí",Q6/B6,"") | S6: =IF(O6="Sí",MAX(0,B6-Q6),0) -> 0 | T6: =IF(O6="Sí","Desembolsado",IF(K6="No","Pendiente de producto",IF(L6="No","En conformidad",IF(N6="Sí","Listo para solicitar","Falta rendición")))) -> Pendiente de producto | U6: =IF(T6="Desembolsado","Pagado"&IF(P6<>""," el "&RIGHT("0"&DAY(P6),2)&"/"&RIGHT("0"&MONTH(P6),2)&"/"&YEAR(P6),"")&IF(S6>0,". Por rendir: S/ "&FIXED(S6,2),". Rendido al 100 %."),IF(T6="Pendiente de producto","Presentar "&G6&" (vence el "&RIGHT("0"&DAY(I6),2)&"/"&RIGHT("0"&MONTH(I6),2)&"/"&YEAR(I6)&")",IF(T6="En conformidad","Conseguir la opinión técnica del Componente 2 y las conformidades del Coordinador y de FAO",IF(T6="Falta rendición",M6,"La UGP debe pedir el desembolso por escrito a Profonanpe (cl. 9.3)")))) -> Presentar Producto 2 (Parte I y Parte II) (vence el 30/06/2026) | V6: =IF($T6="Desembolsado",$B6,0) -> 0 | W6: =IF($T6="Listo para solicitar",$B6,0) -> 0 | X6: =IF($T6="Falta rendición",$B6,0) -> 0 | Y6: =IF($T6="En conformidad",$B6,0) -> 0 | Z6: =IF($T6="Pendiente de producto",$B6,0) -> 141375 | AA6: • Presentar el Producto 2. • Conformidades técnicas (Componente 2, Coordinación y FAO). • Rendición ≥ 70 % del 1.er desembolso. • Informe de recursos financiados. | AB6: =ROW()-4 -> 2 | AC6: =IF($T6=AC$4,COUNTIF($T$5:$T6,AC$4),"") | AD6: =IF($T6=AD$4,COUNTIF($T$5:$T6,AD$4),"") | AE6: =IF($T6=AE$4,COUNTIF($T$5:$T6,AE$4),"") | AF6: =IF($T6=AF$4,COUNTIF($T$5:$T6,AF$4),"") | AG6: =IF($T6=AG$4,COUNTIF($T$5:$T6,AG$4),"") -> 1
A7: D3 | B7: 117812 | C7: =B7/TotalCARE -> 0.24999894 | D7: 0.25 | E7: 240 | F7: =IF(E7="","Al presentar P4",Inicio+E7) -> 46186 | G7: Producto 3 | H7: P3 | I7: =INDEX(Entregables!$H$5:$H$9,MATCH(H7,Entregables!$A$5:$A$9,0)) -> 46374 | J7: =IF(E7="",0,I7-F7) -> 188 | K7: =IF(Entregables!L8="Sí","Sí","No") -> No | L7: =IF(Entregables!S8="Aprobado","Sí","No") -> No | M7: ="Rendir el 100 % del 1.er desembolso (S/ "&FIXED(B5,2)&") y al menos el "&TEXT(Rendicion*100,"0")&" % del 2.º (S/ "&FIXED(B6*Rendicion,2)&"). Informe de recursos financiados." -> Rendir el 100 % del 1.er desembolso (S/ 141,375.00) y al menos el 70 % del 2.º (S/ 98,962.50). Informe de recursos financiados. | N7: =IF(AND(Q5>=B5-0.005,Q6>=B6*Rendicion-0.005),"Sí","No") -> No | O7: No | Q7: 0 | R7: =IF(O7="Sí",Q7/B7,"") | S7: =IF(O7="Sí",MAX(0,B7-Q7),0) -> 0 | T7: =IF(O7="Sí","Desembolsado",IF(K7="No","Pendiente de producto",IF(L7="No","En conformidad",IF(N7="Sí","Listo para solicitar","Falta rendición")))) -> Pendiente de producto | U7: =IF(T7="Desembolsado","Pagado"&IF(P7<>""," el "&RIGHT("0"&DAY(P7),2)&"/"&RIGHT("0"&MONTH(P7),2)&"/"&YEAR(P7),"")&IF(S7>0,". Por rendir: S/ "&FIXED(S7,2),". Rendido al 100 %."),IF(T7="Pendiente de producto","Presentar "&G7&" (vence el "&RIGHT("0"&DAY(I7),2)&"/"&RIGHT("0"&MONTH(I7),2)&"/"&YEAR(I7)&")",IF(T7="En conformidad","Conseguir la opinión técnica del Componente 2 y las conformidades del Coordinador y de FAO",IF(T7="Falta rendición",M7,"La UGP debe pedir el desembolso por escrito a Profonanpe (cl. 9.3)")))) -> Presentar Producto 3 (vence el 18/12/2026) | V7: =IF($T7="Desembolsado",$B7,0) -> 0 | W7: =IF($T7="Listo para solicitar",$B7,0) -> 0 | X7: =IF($T7="Falta rendición",$B7,0) -> 0 | Y7: =IF($T7="En conformidad",$B7,0) -> 0 | Z7: =IF($T7="Pendiente de producto",$B7,0) -> 117812 | AA7: • Presentar el Producto 3. • Conformidades técnicas (Componente 2, Coordinación y FAO). • Rendición del 30 % restante del 1.º y ≥ 70 % del 2.º. • Informe de recursos financiados. | AB7: =ROW()-4 -> 3 | AC7: =IF($T7=AC$4,COUNTIF($T$5:$T7,AC$4),"") | AD7: =IF($T7=AD$4,COUNTIF($T$5:$T7,AD$4),"") | AE7: =IF($T7=AE$4,COUNTIF($T$5:$T7,AE$4),"") | AF7: =IF($T7=AF$4,COUNTIF($T$5:$T7,AF$4),"") | AG7: =IF($T7=AG$4,COUNTIF($T$5:$T7,AG$4),"") -> 2
A8: D4 | B8: 70688 | C8: =B8/TotalCARE -> 0.15000106 | D8: 0.15 | F8: =IF(E8="","Al presentar P4",Inicio+E8) -> Al presentar P4 | G8: Producto 4 | H8: P4 | I8: =INDEX(Entregables!$H$5:$H$9,MATCH(H8,Entregables!$A$5:$A$9,0)) -> 46507 | J8: =IF(E8="",0,I8-F8) -> 0 | K8: =IF(Entregables!L9="Sí","Sí","No") -> No | L8: =IF(Entregables!S9="Aprobado","Sí","No") -> No | M8: ="Rendir el 100 % del 2.º desembolso (S/ "&FIXED(B6,2)&") y al menos el "&TEXT(Rendicion*100,"0")&" % del 3.º (S/ "&FIXED(B7*Rendicion,2)&"). Informe de recursos financiados o de contrapartida." -> Rendir el 100 % del 2.º desembolso (S/ 141,375.00) y al menos el 70 % del 3.º (S/ 82,468.40). Informe de recursos financiados o de contrapartida. | N8: =IF(AND(Q6>=B6-0.005,Q7>=B7*Rendicion-0.005),"Sí","No") -> No | O8: No | Q8: 0 | R8: =IF(O8="Sí",Q8/B8,"") | S8: =IF(O8="Sí",MAX(0,B8-Q8),0) -> 0 | T8: =IF(O8="Sí","Desembolsado",IF(K8="No","Pendiente de producto",IF(L8="No","En conformidad",IF(N8="Sí","Listo para solicitar","Falta rendición")))) -> Pendiente de producto | U8: =IF(T8="Desembolsado","Pagado"&IF(P8<>""," el "&RIGHT("0"&DAY(P8),2)&"/"&RIGHT("0"&MONTH(P8),2)&"/"&YEAR(P8),"")&IF(S8>0,". Por rendir: S/ "&FIXED(S8,2),". Rendido al 100 %."),IF(T8="Pendiente de producto","Presentar "&G8&" (vence el "&RIGHT("0"&DAY(I8),2)&"/"&RIGHT("0"&MONTH(I8),2)&"/"&YEAR(I8)&")",IF(T8="En conformidad","Conseguir la opinión técnica del Componente 2 y las conformidades del Coordinador y de FAO",IF(T8="Falta rendición",M8,"La UGP debe pedir el desembolso por escrito a Profonanpe (cl. 9.3)")))) -> Presentar Producto 4 (vence el 30/04/2027) | V8: =IF($T8="Desembolsado",$B8,0) -> 0 | W8: =IF($T8="Listo para solicitar",$B8,0) -> 0 | X8: =IF($T8="Falta rendición",$B8,0) -> 0 | Y8: =IF($T8="En conformidad",$B8,0) -> 0 | Z8: =IF($T8="Pendiente de producto",$B8,0) -> 70688 | AA8: • Presentar el Producto 4 (informe final). • Conformidades técnicas (Componente 2, Coordinación y FAO). • Rendición del 30 % restante del 2.º y ≥ 70 % del 3.º. • Informe de recursos financiados o de contrapartida. • El saldo del 4.º se rinde a más tardar 10 días después del informe final (cl. 9.2). | AB8: =ROW()-4 -> 4 | AC8: =IF($T8=AC$4,COUNTIF($T$5:$T8,AC$4),"") | AD8: =IF($T8=AD$4,COUNTIF($T$5:$T8,AD$4),"") | AE8: =IF($T8=AE$4,COUNTIF($T$5:$T8,AE$4),"") | AF8: =IF($T8=AF$4,COUNTIF($T$5:$T8,AF$4),"") | AG8: =IF($T8=AG$4,COUNTIF($T$5:$T8,AG$4),"") -> 3
A9: Total | B9: =SUM(B5:B8) -> 471250 | C9: =SUM(C5:C8) -> 1 | D9: =SUM(D5:D8) -> 1 | Q9: =SUM(Q5:Q8) -> 0 | S9: =SUM(S5:S8) -> 0 | V9: =SUM(V5:V8) -> 0 | W9: =SUM(W5:W8) -> 0 | X9: =SUM(X5:X8) -> 0 | Y9: =SUM(Y5:Y8) -> 141375 | Z9: =SUM(Z5:Z8) -> 329875
A11: ="Aparte, la UGP compra insumos y equipos por S/ "&FIXED(Parámetros!C9,2)&" que no se descuentan del convenio (cl. 9.1): tope total de Profonanpe S/ "&FIXED(Parámetros!C10,2)&" (cl. 5.2.1)." -> Aparte, la UGP compra insumos y equipos por S/ 40,000.00 que no se descuentan del convenio (cl. 9.1): tope total de Profonanpe S/ 511,250.00 (cl. 5.2.1).
A12: La «fecha según 9.1» es la del convenio original y no fue actualizada por la Adenda: hoy cae antes del producto que habilita cada pago. En la práctica el pago llega tras presentar el producto y reunir conformidades.
A13: Estado: Pendiente de producto → En conformidad (producto presentado, falta aprobación) → Falta rendición (aprobado, pero no se cumple la rendición previa) → Listo para solicitar → Desembolsado.
A14: Se asume que el Desembolso 2 requiere las dos partes del Producto 2 (punto por aclarar con Profonanpe, ver hoja Dudas).

Sheet Vistas
B1: ← Volver al Panel
B2: Vistas por estado
B3: Destino de los botones del Panel. Cada bloque lista los productos o desembolsos en ese estado, según la fecha de referencia.
B4: Índice
B5: Productos: | C5: Todos | D5: Por entregar | E5: Por vencer | F5: Vencido | G5: En revisión | H5: Observado | I5: Aprobado
B7: Desembolsos: | C7: Todos | D7: Desembolsado | E7: Listo para solicitar | F7: Falta rendición | G7: En conformidad | H7: Pendiente de producto
B10: ="PRODUCTOS · TODOS LOS PRODUCTOS ("&5&")" -> PRODUCTOS · TODOS LOS PRODUCTOS (5) | H10: ↑ Índice | I10: ← Panel
B11: Producto | C11: Título | D11: Fecha límite | E11: Días restantes | F11: Estado | G11: Situación | H11: Desembolso | I11: Fecha de entrega
B12: =IFERROR(INDEX(Entregables!$D$5:$D$9,MATCH(1,Entregables!$AC$5:$AC$9,0)),"") -> Producto 1 | C12: =IFERROR(INDEX(Entregables!$E$5:$E$9,MATCH(1,Entregables!$AC$5:$AC$9,0)),"") -> Plan de trabajo y cronograma | D12: =IFERROR(INDEX(Entregables!$H$5:$H$9,MATCH(1,Entregables!$AC$5:$AC$9,0)),"") -> 46011 | E12: =IFERROR(INDEX(Entregables!$R$5:$R$9,MATCH(1,Entregables!$AC$5:$AC$9,0)),"") -> -298 | F12: =IFERROR(INDEX(Entregables!$S$5:$S$9,MATCH(1,Entregables!$AC$5:$AC$9,0)),"") -> En revisión | G12: =IFERROR(INDEX(Entregables!$T$5:$T$9,MATCH(1,Entregables!$AC$5:$AC$9,0)),"") -> Presentado el 30/11/2025; espera conformidad UGP/FAO | H12: =IFERROR(INDEX(Entregables!$K$5:$K$9,MATCH(1,Entregables!$AC$5:$AC$9,0)),"") -> D1 | I12: =IFERROR(IF(INDEX(Entregables!$M$5:$M$9,MATCH(1,Entregables!$AC$5:$AC$9,0))="","",INDEX(Entregables!$M$5:$M$9,MATCH(1,Entregables!$AC$5:$AC$9,0))),"") -> 45991
B13: =IFERROR(INDEX(Entregables!$D$5:$D$9,MATCH(2,Entregables!$AC$5:$AC$9,0)),"") -> Producto 2 · Parte I | C13: =IFERROR(INDEX(Entregables!$E$5:$E$9,MATCH(2,Entregables!$AC$5:$AC$9,0)),"") -> Plan de capacitación y avances | D13: =IFERROR(INDEX(Entregables!$H$5:$H$9,MATCH(2,Entregables!$AC$5:$AC$9,0)),"") -> 46142 | E13: =IFERROR(INDEX(Entregables!$R$5:$R$9,MATCH(2,Entregables!$AC$5:$AC$9,0)),"") -> -167 | F13: =IFERROR(INDEX(Entregables!$S$5:$S$9,MATCH(2,Entregables!$AC$5:$AC$9,0)),"") -> Vencido | G13: =IFERROR(INDEX(Entregables!$T$5:$T$9,MATCH(2,Entregables!$AC$5:$AC$9,0)),"") -> Venció hace 167 días | H13: =IFERROR(INDEX(Entregables!$K$5:$K$9,MATCH(2,Entregables!$AC$5:$AC$9,0)),"") -> D2 | I13: =IFERROR(IF(INDEX(Entregables!$M$5:$M$9,MATCH(2,Entregables!$AC$5:$AC$9,0))="","",INDEX(Entregables!$M$5:$M$9,MATCH(2,Entregables!$AC$5:$AC$9,0))),"")
B14: =IFERROR(INDEX(Entregables!$D$5:$D$9,MATCH(3,Entregables!$AC$5:$AC$9,0)),"") -> Producto 2 · Parte II | C14: =IFERROR(INDEX(Entregables!$E$5:$E$9,MATCH(3,Entregables!$AC$5:$AC$9,0)),"") -> Plan de recuperación y fichas | D14: =IFERROR(INDEX(Entregables!$H$5:$H$9,MATCH(3,Entregables!$AC$5:$AC$9,0)),"") -> 46203 | E14: =IFERROR(INDEX(Entregables!$R$5:$R$9,MATCH(3,Entregables!$AC$5:$AC$9,0)),"") -> -106 | F14: =IFERROR(INDEX(Entregables!$S$5:$S$9,MATCH(3,Entregables!$AC$5:$AC$9,0)),"") -> Vencido | G14: =IFERROR(INDEX(Entregables!$T$5:$T$9,MATCH(3,Entregables!$AC$5:$AC$9,0)),"") -> Venció hace 106 días | H14: =IFERROR(INDEX(Entregables!$K$5:$K$9,MATCH(3,Entregables!$AC$5:$AC$9,0)),"") -> D2 | I14: =IFERROR(IF(INDEX(Entregables!$M$5:$M$9,MATCH(3,Entregables!$AC$5:$AC$9,0))="","",INDEX(Entregables!$M$5:$M$9,MATCH(3,Entregables!$AC$5:$AC$9,0))),"")
B15: =IFERROR(INDEX(Entregables!$D$5:$D$9,MATCH(4,Entregables!$AC$5:$AC$9,0)),"") -> Producto 3 | C15: =IFERROR(INDEX(Entregables!$E$5:$E$9,MATCH(4,Entregables!$AC$5:$AC$9,0)),"") -> Pasantía, plantaciones y planes de vida | D15: =IFERROR(INDEX(Entregables!$H$5:$H$9,MATCH(4,Entregables!$AC$5:$AC$9,0)),"") -> 46374 | E15: =IFERROR(INDEX(Entregables!$R$5:$R$9,MATCH(4,Entregables!$AC$5:$AC$9,0)),"") -> 65 | F15: =IFERROR(INDEX(Entregables!$S$5:$S$9,MATCH(4,Entregables!$AC$5:$AC$9,0)),"") -> Por entregar | G15: =IFERROR(INDEX(Entregables!$T$5:$T$9,MATCH(4,Entregables!$AC$5:$AC$9,0)),"") -> Vence en 65 días | H15: =IFERROR(INDEX(Entregables!$K$5:$K$9,MATCH(4,Entregables!$AC$5:$AC$9,0)),"") -> D3 | I15: =IFERROR(IF(INDEX(Entregables!$M$5:$M$9,MATCH(4,Entregables!$AC$5:$AC$9,0))="","",INDEX(Entregables!$M$5:$M$9,MATCH(4,Entregables!$AC$5:$AC$9,0))),"")
B16: =IFERROR(INDEX(Entregables!$D$5:$D$9,MATCH(5,Entregables!$AC$5:$AC$9,0)),"") -> Producto 4 | C16: =IFERROR(INDEX(Entregables!$E$5:$E$9,MATCH(5,Entregables!$AC$5:$AC$9,0)),"") -> Informe final y resultados | D16: =IFERROR(INDEX(Entregables!$H$5:$H$9,MATCH(5,Entregables!$AC$5:$AC$9,0)),"") -> 46507 | E16: =IFERROR(INDEX(Entregables!$R$5:$R$9,MATCH(5,Entregables!$AC$5:$AC$9,0)),"") -> 198 | F16: =IFERROR(INDEX(Entregables!$S$5:$S$9,MATCH(5,Entregables!$AC$5:$AC$9,0)),"") -> Por entregar | G16: =IFERROR(INDEX(Entregables!$T$5:$T$9,MATCH(5,Entregables!$AC$5:$AC$9,0)),"") -> Vence en 198 días | H16: =IFERROR(INDEX(Entregables!$K$5:$K$9,MATCH(5,Entregables!$AC$5:$AC$9,0)),"") -> D4 | I16: =IFERROR(IF(INDEX(Entregables!$M$5:$M$9,MATCH(5,Entregables!$AC$5:$AC$9,0))="","",INDEX(Entregables!$M$5:$M$9,MATCH(5,Entregables!$AC$5:$AC$9,0))),"")
B18: ="PRODUCTOS · POR ENTREGAR ("&'Datos gráficos'!$C$27&")" -> PRODUCTOS · POR ENTREGAR (2) | H18: ↑ Índice | I18: ← Panel
B19: Producto | C19: Título | D19: Fecha límite | E19: Días restantes | F19: Estado | G19: Situación | H19: Desembolso | I19: Fecha de entrega
B20: =IFERROR(INDEX(Entregables!$D$5:$D$9,MATCH(1,Entregables!$AD$5:$AD$9,0)),"Ningún producto en este estado.") -> Producto 3 | C20: =IFERROR(INDEX(Entregables!$E$5:$E$9,MATCH(1,Entregables!$AD$5:$AD$9,0)),"") -> Pasantía, plantaciones y planes de vida | D20: =IFERROR(INDEX(Entregables!$H$5:$H$9,MATCH(1,Entregables!$AD$5:$AD$9,0)),"") -> 46374 | E20: =IFERROR(INDEX(Entregables!$R$5:$R$9,MATCH(1,Entregables!$AD$5:$AD$9,0)),"") -> 65 | F20: =IFERROR(INDEX(Entregables!$S$5:$S$9,MATCH(1,Entregables!$AD$5:$AD$9,0)),"") -> Por entregar | G20: =IFERROR(INDEX(Entregables!$T$5:$T$9,MATCH(1,Entregables!$AD$5:$AD$9,0)),"") -> Vence en 65 días | H20: =IFERROR(INDEX(Entregables!$K$5:$K$9,MATCH(1,Entregables!$AD$5:$AD$9,0)),"") -> D3 | I20: =IFERROR(IF(INDEX(Entregables!$M$5:$M$9,MATCH(1,Entregables!$AD$5:$AD$9,0))="","",INDEX(Entregables!$M$5:$M$9,MATCH(1,Entregables!$AD$5:$AD$9,0))),"")
B21: =IFERROR(INDEX(Entregables!$D$5:$D$9,MATCH(2,Entregables!$AD$5:$AD$9,0)),"") -> Producto 4 | C21: =IFERROR(INDEX(Entregables!$E$5:$E$9,MATCH(2,Entregables!$AD$5:$AD$9,0)),"") -> Informe final y resultados | D21: =IFERROR(INDEX(Entregables!$H$5:$H$9,MATCH(2,Entregables!$AD$5:$AD$9,0)),"") -> 46507 | E21: =IFERROR(INDEX(Entregables!$R$5:$R$9,MATCH(2,Entregables!$AD$5:$AD$9,0)),"") -> 198 | F21: =IFERROR(INDEX(Entregables!$S$5:$S$9,MATCH(2,Entregables!$AD$5:$AD$9,0)),"") -> Por entregar | G21: =IFERROR(INDEX(Entregables!$T$5:$T$9,MATCH(2,Entregables!$AD$5:$AD$9,0)),"") -> Vence en 198 días | H21: =IFERROR(INDEX(Entregables!$K$5:$K$9,MATCH(2,Entregables!$AD$5:$AD$9,0)),"") -> D4 | I21: =IFERROR(IF(INDEX(Entregables!$M$5:$M$9,MATCH(2,Entregables!$AD$5:$AD$9,0))="","",INDEX(Entregables!$M$5:$M$9,MATCH(2,Entregables!$AD$5:$AD$9,0))),"")
B22: =IFERROR(INDEX(Entregables!$D$5:$D$9,MATCH(3,Entregables!$AD$5:$AD$9,0)),"") | C22: =IFERROR(INDEX(Entregables!$E$5:$E$9,MATCH(3,Entregables!$AD$5:$AD$9,0)),"") | D22: =IFERROR(INDEX(Entregables!$H$5:$H$9,MATCH(3,Entregables!$AD$5:$AD$9,0)),"") | E22: =IFERROR(INDEX(Entregables!$R$5:$R$9,MATCH(3,Entregables!$AD$5:$AD$9,0)),"") | F22: =IFERROR(INDEX(Entregables!$S$5:$S$9,MATCH(3,Entregables!$AD$5:$AD$9,0)),"") | G22: =IFERROR(INDEX(Entregables!$T$5:$T$9,MATCH(3,Entregables!$AD$5:$AD$9,0)),"") | H22: =IFERROR(INDEX(Entregables!$K$5:$K$9,MATCH(3,Entregables!$AD$5:$AD$9,0)),"") | I22: =IFERROR(IF(INDEX(Entregables!$M$5:$M$9,MATCH(3,Entregables!$AD$5:$AD$9,0))="","",INDEX(Entregables!$M$5:$M$9,MATCH(3,Entregables!$AD$5:$AD$9,0))),"")
B23: =IFERROR(INDEX(Entregables!$D$5:$D$9,MATCH(4,Entregables!$AD$5:$AD$9,0)),"") | C23: =IFERROR(INDEX(Entregables!$E$5:$E$9,MATCH(4,Entregables!$AD$5:$AD$9,0)),"") | D23: =IFERROR(INDEX(Entregables!$H$5:$H$9,MATCH(4,Entregables!$AD$5:$AD$9,0)),"") | E23: =IFERROR(INDEX(Entregables!$R$5:$R$9,MATCH(4,Entregables!$AD$5:$AD$9,0)),"") | F23: =IFERROR(INDEX(Entregables!$S$5:$S$9,MATCH(4,Entregables!$AD$5:$AD$9,0)),"") | G23: =IFERROR(INDEX(Entregables!$T$5:$T$9,MATCH(4,Entregables!$AD$5:$AD$9,0)),"") | H23: =IFERROR(INDEX(Entregables!$K$5:$K$9,MATCH(4,Entregables!$AD$5:$AD$9,0)),"") | I23: =IFERROR(IF(INDEX(Entregables!$M$5:$M$9,MATCH(4,Entregables!$AD$5:$AD$9,0))="","",INDEX(Entregables!$M$5:$M$9,MATCH(4,Entregables!$AD$5:$AD$9,0))),"")
B24: =IFERROR(INDEX(Entregables!$D$5:$D$9,MATCH(5,Entregables!$AD$5:$AD$9,0)),"") | C24: =IFERROR(INDEX(Entregables!$E$5:$E$9,MATCH(5,Entregables!$AD$5:$AD$9,0)),"") | D24: =IFERROR(INDEX(Entregables!$H$5:$H$9,MATCH(5,Entregables!$AD$5:$AD$9,0)),"") | E24: =IFERROR(INDEX(Entregables!$R$5:$R$9,MATCH(5,Entregables!$AD$5:$AD$9,0)),"") | F24: =IFERROR(INDEX(Entregables!$S$5:$S$9,MATCH(5,Entregables!$AD$5:$AD$9,0)),"") | G24: =IFERROR(INDEX(Entregables!$T$5:$T$9,MATCH(5,Entregables!$AD$5:$AD$9,0)),"") | H24: =IFERROR(INDEX(Entregables!$K$5:$K$9,MATCH(5,Entregables!$AD$5:$AD$9,0)),"") | I24: =IFERROR(IF(INDEX(Entregables!$M$5:$M$9,MATCH(5,Entregables!$AD$5:$AD$9,0))="","",INDEX(Entregables!$M$5:$M$9,MATCH(5,Entregables!$AD$5:$AD$9,0))),"")
B26: ="PRODUCTOS · POR VENCER ("&'Datos gráficos'!$C$28&")" -> PRODUCTOS · POR VENCER (0) | H26: ↑ Índice | I26: ← Panel
B27: Producto | C27: Título | D27: Fecha límite | E27: Días restantes | F27: Estado | G27: Situación | H27: Desembolso | I27: Fecha de entrega
B28: =IFERROR(INDEX(Entregables!$D$5:$D$9,MATCH(1,Entregables!$AE$5:$AE$9,0)),"Ningún producto en este estado.") -> Ningún producto en este estado. | C28: =IFERROR(INDEX(Entregables!$E$5:$E$9,MATCH(1,Entregables!$AE$5:$AE$9,0)),"") | D28: =IFERROR(INDEX(Entregables!$H$5:$H$9,MATCH(1,Entregables!$AE$5:$AE$9,0)),"") | E28: =IFERROR(INDEX(Entregables!$R$5:$R$9,MATCH(1,Entregables!$AE$5:$AE$9,0)),"") | F28: =IFERROR(INDEX(Entregables!$S$5:$S$9,MATCH(1,Entregables!$AE$5:$AE$9,0)),"") | G28: =IFERROR(INDEX(Entregables!$T$5:$T$9,MATCH(1,Entregables!$AE$5:$AE$9,0)),"") | H28: =IFERROR(INDEX(Entregables!$K$5:$K$9,MATCH(1,Entregables!$AE$5:$AE$9,0)),"") | I28: =IFERROR(IF(INDEX(Entregables!$M$5:$M$9,MATCH(1,Entregables!$AE$5:$AE$9,0))="","",INDEX(Entregables!$M$5:$M$9,MATCH(1,Entregables!$AE$5:$AE$9,0))),"")
B29: =IFERROR(INDEX(Entregables!$D$5:$D$9,MATCH(2,Entregables!$AE$5:$AE$9,0)),"") | C29: =IFERROR(INDEX(Entregables!$E$5:$E$9,MATCH(2,Entregables!$AE$5:$AE$9,0)),"") | D29: =IFERROR(INDEX(Entregables!$H$5:$H$9,MATCH(2,Entregables!$AE$5:$AE$9,0)),"") | E29: =IFERROR(INDEX(Entregables!$R$5:$R$9,MATCH(2,Entregables!$AE$5:$AE$9,0)),"") | F29: =IFERROR(INDEX(Entregables!$S$5:$S$9,MATCH(2,Entregables!$AE$5:$AE$9,0)),"") | G29: =IFERROR(INDEX(Entregables!$T$5:$T$9,MATCH(2,Entregables!$AE$5:$AE$9,0)),"") | H29: =IFERROR(INDEX(Entregables!$K$5:$K$9,MATCH(2,Entregables!$AE$5:$AE$9,0)),"") | I29: =IFERROR(IF(INDEX(Entregables!$M$5:$M$9,MATCH(2,Entregables!$AE$5:$AE$9,0))="","",INDEX(Entregables!$M$5:$M$9,MATCH(2,Entregables!$AE$5:$AE$9,0))),"")
B30: =IFERROR(INDEX(Entregables!$D$5:$D$9,MATCH(3,Entregables!$AE$5:$AE$9,0)),"") | C30: =IFERROR(INDEX(Entregables!$E$5:$E$9,MATCH(3,Entregables!$AE$5:$AE$9,0)),"") | D30: =IFERROR(INDEX(Entregables!$H$5:$H$9,MATCH(3,Entregables!$AE$5:$AE$9,0)),"") | E30: =IFERROR(INDEX(Entregables!$R$5:$R$9,MATCH(3,Entregables!$AE$5:$AE$9,0)),"") | F30: =IFERROR(INDEX(Entregables!$S$5:$S$9,MATCH(3,Entregables!$AE$5:$AE$9,0)),"") | G30: =IFERROR(INDEX(Entregables!$T$5:$T$9,MATCH(3,Entregables!$AE$5:$AE$9,0)),"") | H30: =IFERROR(INDEX(Entregables!$K$5:$K$9,MATCH(3,Entregables!$AE$5:$AE$9,0)),"") | I30: =IFERROR(IF(INDEX(Entregables!$M$5:$M$9,MATCH(3,Entregables!$AE$5:$AE$9,0))="","",INDEX(Entregables!$M$5:$M$9,MATCH(3,Entregables!$AE$5:$AE$9,0))),"")
B31: =IFERROR(INDEX(Entregables!$D$5:$D$9,MATCH(4,Entregables!$AE$5:$AE$9,0)),"") | C31: =IFERROR(INDEX(Entregables!$E$5:$E$9,MATCH(4,Entregables!$AE$5:$AE$9,0)),"") | D31: =IFERROR(INDEX(Entregables!$H$5:$H$9,MATCH(4,Entregables!$AE$5:$AE$9,0)),"") | E31: =IFERROR(INDEX(Entregables!$R$5:$R$9,MATCH(4,Entregables!$AE$5:$AE$9,0)),"") | F31: =IFERROR(INDEX(Entregables!$S$5:$S$9,MATCH(4,Entregables!$AE$5:$AE$9,0)),"") | G31: =IFERROR(INDEX(Entregables!$T$5:$T$9,MATCH(4,Entregables!$AE$5:$AE$9,0)),"") | H31: =IFERROR(INDEX(Entregables!$K$5:$K$9,MATCH(4,Entregables!$AE$5:$AE$9,0)),"") | I31: =IFERROR(IF(INDEX(Entregables!$M$5:$M$9,MATCH(4,Entregables!$AE$5:$AE$9,0))="","",INDEX(Entregables!$M$5:$M$9,MATCH(4,Entregables!$AE$5:$AE$9,0))),"")
B32: =IFERROR(INDEX(Entregables!$D$5:$D$9,MATCH(5,Entregables!$AE$5:$AE$9,0)),"") | C32: =IFERROR(INDEX(Entregables!$E$5:$E$9,MATCH(5,Entregables!$AE$5:$AE$9,0)),"") | D32: =IFERROR(INDEX(Entregables!$H$5:$H$9,MATCH(5,Entregables!$AE$5:$AE$9,0)),"") | E32: =IFERROR(INDEX(Entregables!$R$5:$R$9,MATCH(5,Entregables!$AE$5:$AE$9,0)),"") | F32: =IFERROR(INDEX(Entregables!$S$5:$S$9,MATCH(5,Entregables!$AE$5:$AE$9,0)),"") | G32: =IFERROR(INDEX(Entregables!$T$5:$T$9,MATCH(5,Entregables!$AE$5:$AE$9,0)),"") | H32: =IFERROR(INDEX(Entregables!$K$5:$K$9,MATCH(5,Entregables!$AE$5:$AE$9,0)),"") | I32: =IFERROR(IF(INDEX(Entregables!$M$5:$M$9,MATCH(5,Entregables!$AE$5:$AE$9,0))="","",INDEX(Entregables!$M$5:$M$9,MATCH(5,Entregables!$AE$5:$AE$9,0))),"")
B34: ="PRODUCTOS · VENCIDO ("&'Datos gráficos'!$C$29&")" -> PRODUCTOS · VENCIDO (2) | H34: ↑ Índice | I34: ← Panel
B35: Producto | C35: Título | D35: Fecha límite | E35: Días restantes | F35: Estado | G35: Situación | H35: Desembolso | I35: Fecha de entrega
B36: =IFERROR(INDEX(Entregables!$D$5:$D$9,MATCH(1,Entregables!$AF$5:$AF$9,0)),"Ningún producto en este estado.") -> Producto 2 · Parte I | C36: =IFERROR(INDEX(Entregables!$E$5:$E$9,MATCH(1,Entregables!$AF$5:$AF$9,0)),"") -> Plan de capacitación y avances | D36: =IFERROR(INDEX(Entregables!$H$5:$H$9,MATCH(1,Entregables!$AF$5:$AF$9,0)),"") -> 46142 | E36: =IFERROR(INDEX(Entregables!$R$5:$R$9,MATCH(1,Entregables!$AF$5:$AF$9,0)),"") -> -167 | F36: =IFERROR(INDEX(Entregables!$S$5:$S$9,MATCH(1,Entregables!$AF$5:$AF$9,0)),"") -> Vencido | G36: =IFERROR(INDEX(Entregables!$T$5:$T$9,MATCH(1,Entregables!$AF$5:$AF$9,0)),"") -> Venció hace 167 días | H36: =IFERROR(INDEX(Entregables!$K$5:$K$9,MATCH(1,Entregables!$AF$5:$AF$9,0)),"") -> D2 | I36: =IFERROR(IF(INDEX(Entregables!$M$5:$M$9,MATCH(1,Entregables!$AF$5:$AF$9,0))="","",INDEX(Entregables!$M$5:$M$9,MATCH(1,Entregables!$AF$5:$AF$9,0))),"")
B37: =IFERROR(INDEX(Entregables!$D$5:$D$9,MATCH(2,Entregables!$AF$5:$AF$9,0)),"") -> Producto 2 · Parte II | C37: =IFERROR(INDEX(Entregables!$E$5:$E$9,MATCH(2,Entregables!$AF$5:$AF$9,0)),"") -> Plan de recuperación y fichas | D37: =IFERROR(INDEX(Entregables!$H$5:$H$9,MATCH(2,Entregables!$AF$5:$AF$9,0)),"") -> 46203 | E37: =IFERROR(INDEX(Entregables!$R$5:$R$9,MATCH(2,Entregables!$AF$5:$AF$9,0)),"") -> -106 | F37: =IFERROR(INDEX(Entregables!$S$5:$S$9,MATCH(2,Entregables!$AF$5:$AF$9,0)),"") -> Vencido | G37: =IFERROR(INDEX(Entregables!$T$5:$T$9,MATCH(2,Entregables!$AF$5:$AF$9,0)),"") -> Venció hace 106 días | H37: =IFERROR(INDEX(Entregables!$K$5:$K$9,MATCH(2,Entregables!$AF$5:$AF$9,0)),"") -> D2 | I37: =IFERROR(IF(INDEX(Entregables!$M$5:$M$9,MATCH(2,Entregables!$AF$5:$AF$9,0))="","",INDEX(Entregables!$M$5:$M$9,MATCH(2,Entregables!$AF$5:$AF$9,0))),"")
B38: =IFERROR(INDEX(Entregables!$D$5:$D$9,MATCH(3,Entregables!$AF$5:$AF$9,0)),"") | C38: =IFERROR(INDEX(Entregables!$E$5:$E$9,MATCH(3,Entregables!$AF$5:$AF$9,0)),"") | D38: =IFERROR(INDEX(Entregables!$H$5:$H$9,MATCH(3,Entregables!$AF$5:$AF$9,0)),"") | E38: =IFERROR(INDEX(Entregables!$R$5:$R$9,MATCH(3,Entregables!$AF$5:$AF$9,0)),"") | F38: =IFERROR(INDEX(Entregables!$S$5:$S$9,MATCH(3,Entregables!$AF$5:$AF$9,0)),"") | G38: =IFERROR(INDEX(Entregables!$T$5:$T$9,MATCH(3,Entregables!$AF$5:$AF$9,0)),"") | H38: =IFERROR(INDEX(Entregables!$K$5:$K$9,MATCH(3,Entregables!$AF$5:$AF$9,0)),"") | I38: =IFERROR(IF(INDEX(Entregables!$M$5:$M$9,MATCH(3,Entregables!$AF$5:$AF$9,0))="","",INDEX(Entregables!$M$5:$M$9,MATCH(3,Entregables!$AF$5:$AF$9,0))),"")
B39: =IFERROR(INDEX(Entregables!$D$5:$D$9,MATCH(4,Entregables!$AF$5:$AF$9,0)),"") | C39: =IFERROR(INDEX(Entregables!$E$5:$E$9,MATCH(4,Entregables!$AF$5:$AF$9,0)),"") | D39: =IFERROR(INDEX(Entregables!$H$5:$H$9,MATCH(4,Entregables!$AF$5:$AF$9,0)),"") | E39: =IFERROR(INDEX(Entregables!$R$5:$R$9,MATCH(4,Entregables!$AF$5:$AF$9,0)),"") | F39: =IFERROR(INDEX(Entregables!$S$5:$S$9,MATCH(4,Entregables!$AF$5:$AF$9,0)),"") | G39: =IFERROR(INDEX(Entregables!$T$5:$T$9,MATCH(4,Entregables!$AF$5:$AF$9,0)),"") | H39: =IFERROR(INDEX(Entregables!$K$5:$K$9,MATCH(4,Entregables!$AF$5:$AF$9,0)),"") | I39: =IFERROR(IF(INDEX(Entregables!$M$5:$M$9,MATCH(4,Entregables!$AF$5:$AF$9,0))="","",INDEX(Entregables!$M$5:$M$9,MATCH(4,Entregables!$AF$5:$AF$9,0))),"")
B40: =IFERROR(INDEX(Entregables!$D$5:$D$9,MATCH(5,Entregables!$AF$5:$AF$9,0)),"") | C40: =IFERROR(INDEX(Entregables!$E$5:$E$9,MATCH(5,Entregables!$AF$5:$AF$9,0)),"") | D40: =IFERROR(INDEX(Entregables!$H$5:$H$9,MATCH(5,Entregables!$AF$5:$AF$9,0)),"") | E40: =IFERROR(INDEX(Entregables!$R$5:$R$9,MATCH(5,Entregables!$AF$5:$AF$9,0)),"") | F40: =IFERROR(INDEX(Entregables!$S$5:$S$9,MATCH(5,Entregables!$AF$5:$AF$9,0)),"") | G40: =IFERROR(INDEX(Entregables!$T$5:$T$9,MATCH(5,Entregables!$AF$5:$AF$9,0)),"") | H40: =IFERROR(INDEX(Entregables!$K$5:$K$9,MATCH(5,Entregables!$AF$5:$AF$9,0)),"") | I40: =IFERROR(IF(INDEX(Entregables!$M$5:$M$9,MATCH(5,Entregables!$AF$5:$AF$9,0))="","",INDEX(Entregables!$M$5:$M$9,MATCH(5,Entregables!$AF$5:$AF$9,0))),"")
B42: ="PRODUCTOS · EN REVISIÓN ("&'Datos gráficos'!$C$30&")" -> PRODUCTOS · EN REVISIÓN (1) | H42: ↑ Índice | I42: ← Panel
B43: Producto | C43: Título | D43: Fecha límite | E43: Días restantes | F43: Estado | G43: Situación | H43: Desembolso | I43: Fecha de entrega
B44: =IFERROR(INDEX(Entregables!$D$5:$D$9,MATCH(1,Entregables!$AG$5:$AG$9,0)),"Ningún producto en este estado.") -> Producto 1 | C44: =IFERROR(INDEX(Entregables!$E$5:$E$9,MATCH(1,Entregables!$AG$5:$AG$9,0)),"") -> Plan de trabajo y cronograma | D44: =IFERROR(INDEX(Entregables!$H$5:$H$9,MATCH(1,Entregables!$AG$5:$AG$9,0)),"") -> 46011 | E44: =IFERROR(INDEX(Entregables!$R$5:$R$9,MATCH(1,Entregables!$AG$5:$AG$9,0)),"") -> -298 | F44: =IFERROR(INDEX(Entregables!$S$5:$S$9,MATCH(1,Entregables!$AG$5:$AG$9,0)),"") -> En revisión | G44: =IFERROR(INDEX(Entregables!$T$5:$T$9,MATCH(1,Entregables!$AG$5:$AG$9,0)),"") -> Presentado el 30/11/2025; espera conformidad UGP/FAO | H44: =IFERROR(INDEX(Entregables!$K$5:$K$9,MATCH(1,Entregables!$AG$5:$AG$9,0)),"") -> D1 | I44: =IFERROR(IF(INDEX(Entregables!$M$5:$M$9,MATCH(1,Entregables!$AG$5:$AG$9,0))="","",INDEX(Entregables!$M$5:$M$9,MATCH(1,Entregables!$AG$5:$AG$9,0))),"") -> 45991
B45: =IFERROR(INDEX(Entregables!$D$5:$D$9,MATCH(2,Entregables!$AG$5:$AG$9,0)),"") | C45: =IFERROR(INDEX(Entregables!$E$5:$E$9,MATCH(2,Entregables!$AG$5:$AG$9,0)),"") | D45: =IFERROR(INDEX(Entregables!$H$5:$H$9,MATCH(2,Entregables!$AG$5:$AG$9,0)),"") | E45: =IFERROR(INDEX(Entregables!$R$5:$R$9,MATCH(2,Entregables!$AG$5:$AG$9,0)),"") | F45: =IFERROR(INDEX(Entregables!$S$5:$S$9,MATCH(2,Entregables!$AG$5:$AG$9,0)),"") | G45: =IFERROR(INDEX(Entregables!$T$5:$T$9,MATCH(2,Entregables!$AG$5:$AG$9,0)),"") | H45: =IFERROR(INDEX(Entregables!$K$5:$K$9,MATCH(2,Entregables!$AG$5:$AG$9,0)),"") | I45: =IFERROR(IF(INDEX(Entregables!$M$5:$M$9,MATCH(2,Entregables!$AG$5:$AG$9,0))="","",INDEX(Entregables!$M$5:$M$9,MATCH(2,Entregables!$AG$5:$AG$9,0))),"")
B46: =IFERROR(INDEX(Entregables!$D$5:$D$9,MATCH(3,Entregables!$AG$5:$AG$9,0)),"") | C46: =IFERROR(INDEX(Entregables!$E$5:$E$9,MATCH(3,Entregables!$AG$5:$AG$9,0)),"") | D46: =IFERROR(INDEX(Entregables!$H$5:$H$9,MATCH(3,Entregables!$AG$5:$AG$9,0)),"") | E46: =IFERROR(INDEX(Entregables!$R$5:$R$9,MATCH(3,Entregables!$AG$5:$AG$9,0)),"") | F46: =IFERROR(INDEX(Entregables!$S$5:$S$9,MATCH(3,Entregables!$AG$5:$AG$9,0)),"") | G46: =IFERROR(INDEX(Entregables!$T$5:$T$9,MATCH(3,Entregables!$AG$5:$AG$9,0)),"") | H46: =IFERROR(INDEX(Entregables!$K$5:$K$9,MATCH(3,Entregables!$AG$5:$AG$9,0)),"") | I46: =IFERROR(IF(INDEX(Entregables!$M$5:$M$9,MATCH(3,Entregables!$AG$5:$AG$9,0))="","",INDEX(Entregables!$M$5:$M$9,MATCH(3,Entregables!$AG$5:$AG$9,0))),"")
B47: =IFERROR(INDEX(Entregables!$D$5:$D$9,MATCH(4,Entregables!$AG$5:$AG$9,0)),"") | C47: =IFERROR(INDEX(Entregables!$E$5:$E$9,MATCH(4,Entregables!$AG$5:$AG$9,0)),"") | D47: =IFERROR(INDEX(Entregables!$H$5:$H$9,MATCH(4,Entregables!$AG$5:$AG$9,0)),"") | E47: =IFERROR(INDEX(Entregables!$R$5:$R$9,MATCH(4,Entregables!$AG$5:$AG$9,0)),"") | F47: =IFERROR(INDEX(Entregables!$S$5:$S$9,MATCH(4,Entregables!$AG$5:$AG$9,0)),"") | G47: =IFERROR(INDEX(Entregables!$T$5:$T$9,MATCH(4,Entregables!$AG$5:$AG$9,0)),"") | H47: =IFERROR(INDEX(Entregables!$K$5:$K$9,MATCH(4,Entregables!$AG$5:$AG$9,0)),"") | I47: =IFERROR(IF(INDEX(Entregables!$M$5:$M$9,MATCH(4,Entregables!$AG$5:$AG$9,0))="","",INDEX(Entregables!$M$5:$M$9,MATCH(4,Entregables!$AG$5:$AG$9,0))),"")
B48: =IFERROR(INDEX(Entregables!$D$5:$D$9,MATCH(5,Entregables!$AG$5:$AG$9,0)),"") | C48: =IFERROR(INDEX(Entregables!$E$5:$E$9,MATCH(5,Entregables!$AG$5:$AG$9,0)),"") | D48: =IFERROR(INDEX(Entregables!$H$5:$H$9,MATCH(5,Entregables!$AG$5:$AG$9,0)),"") | E48: =IFERROR(INDEX(Entregables!$R$5:$R$9,MATCH(5,Entregables!$AG$5:$AG$9,0)),"") | F48: =IFERROR(INDEX(Entregables!$S$5:$S$9,MATCH(5,Entregables!$AG$5:$AG$9,0)),"") | G48: =IFERROR(INDEX(Entregables!$T$5:$T$9,MATCH(5,Entregables!$AG$5:$AG$9,0)),"") | H48: =IFERROR(INDEX(Entregables!$K$5:$K$9,MATCH(5,Entregables!$AG$5:$AG$9,0)),"") | I48: =IFERROR(IF(INDEX(Entregables!$M$5:$M$9,MATCH(5,Entregables!$AG$5:$AG$9,0))="","",INDEX(Entregables!$M$5:$M$9,MATCH(5,Entregables!$AG$5:$AG$9,0))),"")
B50: ="PRODUCTOS · OBSERVADO ("&'Datos gráficos'!$C$31&")" -> PRODUCTOS · OBSERVADO (0) | H50: ↑ Índice | I50: ← Panel
B51: Producto | C51: Título | D51: Fecha límite | E51: Días restantes | F51: Estado | G51: Situación | H51: Desembolso | I51: Fecha de entrega
B52: =IFERROR(INDEX(Entregables!$D$5:$D$9,MATCH(1,Entregables!$AH$5:$AH$9,0)),"Ningún producto en este estado.") -> Ningún producto en este estado. | C52: =IFERROR(INDEX(Entregables!$E$5:$E$9,MATCH(1,Entregables!$AH$5:$AH$9,0)),"") | D52: =IFERROR(INDEX(Entregables!$H$5:$H$9,MATCH(1,Entregables!$AH$5:$AH$9,0)),"") | E52: =IFERROR(INDEX(Entregables!$R$5:$R$9,MATCH(1,Entregables!$AH$5:$AH$9,0)),"") | F52: =IFERROR(INDEX(Entregables!$S$5:$S$9,MATCH(1,Entregables!$AH$5:$AH$9,0)),"") | G52: =IFERROR(INDEX(Entregables!$T$5:$T$9,MATCH(1,Entregables!$AH$5:$AH$9,0)),"") | H52: =IFERROR(INDEX(Entregables!$K$5:$K$9,MATCH(1,Entregables!$AH$5:$AH$9,0)),"") | I52: =IFERROR(IF(INDEX(Entregables!$M$5:$M$9,MATCH(1,Entregables!$AH$5:$AH$9,0))="","",INDEX(Entregables!$M$5:$M$9,MATCH(1,Entregables!$AH$5:$AH$9,0))),"")
B53: =IFERROR(INDEX(Entregables!$D$5:$D$9,MATCH(2,Entregables!$AH$5:$AH$9,0)),"") | C53: =IFERROR(INDEX(Entregables!$E$5:$E$9,MATCH(2,Entregables!$AH$5:$AH$9,0)),"") | D53: =IFERROR(INDEX(Entregables!$H$5:$H$9,MATCH(2,Entregables!$AH$5:$AH$9,0)),"") | E53: =IFERROR(INDEX(Entregables!$R$5:$R$9,MATCH(2,Entregables!$AH$5:$AH$9,0)),"") | F53: =IFERROR(INDEX(Entregables!$S$5:$S$9,MATCH(2,Entregables!$AH$5:$AH$9,0)),"") | G53: =IFERROR(INDEX(Entregables!$T$5:$T$9,MATCH(2,Entregables!$AH$5:$AH$9,0)),"") | H53: =IFERROR(INDEX(Entregables!$K$5:$K$9,MATCH(2,Entregables!$AH$5:$AH$9,0)),"") | I53: =IFERROR(IF(INDEX(Entregables!$M$5:$M$9,MATCH(2,Entregables!$AH$5:$AH$9,0))="","",INDEX(Entregables!$M$5:$M$9,MATCH(2,Entregables!$AH$5:$AH$9,0))),"")
B54: =IFERROR(INDEX(Entregables!$D$5:$D$9,MATCH(3,Entregables!$AH$5:$AH$9,0)),"") | C54: =IFERROR(INDEX(Entregables!$E$5:$E$9,MATCH(3,Entregables!$AH$5:$AH$9,0)),"") | D54: =IFERROR(INDEX(Entregables!$H$5:$H$9,MATCH(3,Entregables!$AH$5:$AH$9,0)),"") | E54: =IFERROR(INDEX(Entregables!$R$5:$R$9,MATCH(3,Entregables!$AH$5:$AH$9,0)),"") | F54: =IFERROR(INDEX(Entregables!$S$5:$S$9,MATCH(3,Entregables!$AH$5:$AH$9,0)),"") | G54: =IFERROR(INDEX(Entregables!$T$5:$T$9,MATCH(3,Entregables!$AH$5:$AH$9,0)),"") | H54: =IFERROR(INDEX(Entregables!$K$5:$K$9,MATCH(3,Entregables!$AH$5:$AH$9,0)),"") | I54: =IFERROR(IF(INDEX(Entregables!$M$5:$M$9,MATCH(3,Entregables!$AH$5:$AH$9,0))="","",INDEX(Entregables!$M$5:$M$9,MATCH(3,Entregables!$AH$5:$AH$9,0))),"")
B55: =IFERROR(INDEX(Entregables!$D$5:$D$9,MATCH(4,Entregables!$AH$5:$AH$9,0)),"") | C55: =IFERROR(INDEX(Entregables!$E$5:$E$9,MATCH(4,Entregables!$AH$5:$AH$9,0)),"") | D55: =IFERROR(INDEX(Entregables!$H$5:$H$9,MATCH(4,Entregables!$AH$5:$AH$9,0)),"") | E55: =IFERROR(INDEX(Entregables!$R$5:$R$9,MATCH(4,Entregables!$AH$5:$AH$9,0)),"") | F55: =IFERROR(INDEX(Entregables!$S$5:$S$9,MATCH(4,Entregables!$AH$5:$AH$9,0)),"") | G55: =IFERROR(INDEX(Entregables!$T$5:$T$9,MATCH(4,Entregables!$AH$5:$AH$9,0)),"") | H55: =IFERROR(INDEX(Entregables!$K$5:$K$9,MATCH(4,Entregables!$AH$5:$AH$9,0)),"") | I55: =IFERROR(IF(INDEX(Entregables!$M$5:$M$9,MATCH(4,Entregables!$AH$5:$AH$9,0))="","",INDEX(Entregables!$M$5:$M$9,MATCH(4,Entregables!$AH$5:$AH$9,0))),"")
B56: =IFERROR(INDEX(Entregables!$D$5:$D$9,MATCH(5,Entregables!$AH$5:$AH$9,0)),"") | C56: =IFERROR(INDEX(Entregables!$E$5:$E$9,MATCH(5,Entregables!$AH$5:$AH$9,0)),"") | D56: =IFERROR(INDEX(Entregables!$H$5:$H$9,MATCH(5,Entregables!$AH$5:$AH$9,0)),"") | E56: =IFERROR(INDEX(Entregables!$R$5:$R$9,MATCH(5,Entregables!$AH$5:$AH$9,0)),"") | F56: =IFERROR(INDEX(Entregables!$S$5:$S$9,MATCH(5,Entregables!$AH$5:$AH$9,0)),"") | G56: =IFERROR(INDEX(Entregables!$T$5:$T$9,MATCH(5,Entregables!$AH$5:$AH$9,0)),"") | H56: =IFERROR(INDEX(Entregables!$K$5:$K$9,MATCH(5,Entregables!$AH$5:$AH$9,0)),"") | I56: =IFERROR(IF(INDEX(Entregables!$M$5:$M$9,MATCH(5,Entregables!$AH$5:$AH$9,0))="","",INDEX(Entregables!$M$5:$M$9,MATCH(5,Entregables!$AH$5:$AH$9,0))),"")
B58: ="PRODUCTOS · APROBADO ("&'Datos gráficos'!$C$32&")" -> PRODUCTOS · APROBADO (0) | H58: ↑ Índice | I58: ← Panel
B59: Producto | C59: Título | D59: Fecha límite | E59: Días restantes | F59: Estado | G59: Situación | H59: Desembolso | I59: Fecha de entrega
B60: =IFERROR(INDEX(Entregables!$D$5:$D$9,MATCH(1,Entregables!$AI$5:$AI$9,0)),"Ningún producto en este estado.") -> Ningún producto en este estado. | C60: =IFERROR(INDEX(Entregables!$E$5:$E$9,MATCH(1,Entregables!$AI$5:$AI$9,0)),"") | D60: =IFERROR(INDEX(Entregables!$H$5:$H$9,MATCH(1,Entregables!$AI$5:$AI$9,0)),"") | E60: =IFERROR(INDEX(Entregables!$R$5:$R$9,MATCH(1,Entregables!$AI$5:$AI$9,0)),"") | F60: =IFERROR(INDEX(Entregables!$S$5:$S$9,MATCH(1,Entregables!$AI$5:$AI$9,0)),"") | G60: =IFERROR(INDEX(Entregables!$T$5:$T$9,MATCH(1,Entregables!$AI$5:$AI$9,0)),"") | H60: =IFERROR(INDEX(Entregables!$K$5:$K$9,MATCH(1,Entregables!$AI$5:$AI$9,0)),"") | I60: =IFERROR(IF(INDEX(Entregables!$M$5:$M$9,MATCH(1,Entregables!$AI$5:$AI$9,0))="","",INDEX(Entregables!$M$5:$M$9,MATCH(1,Entregables!$AI$5:$AI$9,0))),"")
B61: =IFERROR(INDEX(Entregables!$D$5:$D$9,MATCH(2,Entregables!$AI$5:$AI$9,0)),"") | C61: =IFERROR(INDEX(Entregables!$E$5:$E$9,MATCH(2,Entregables!$AI$5:$AI$9,0)),"") | D61: =IFERROR(INDEX(Entregables!$H$5:$H$9,MATCH(2,Entregables!$AI$5:$AI$9,0)),"") | E61: =IFERROR(INDEX(Entregables!$R$5:$R$9,MATCH(2,Entregables!$AI$5:$AI$9,0)),"") | F61: =IFERROR(INDEX(Entregables!$S$5:$S$9,MATCH(2,Entregables!$AI$5:$AI$9,0)),"") | G61: =IFERROR(INDEX(Entregables!$T$5:$T$9,MATCH(2,Entregables!$AI$5:$AI$9,0)),"") | H61: =IFERROR(INDEX(Entregables!$K$5:$K$9,MATCH(2,Entregables!$AI$5:$AI$9,0)),"") | I61: =IFERROR(IF(INDEX(Entregables!$M$5:$M$9,MATCH(2,Entregables!$AI$5:$AI$9,0))="","",INDEX(Entregables!$M$5:$M$9,MATCH(2,Entregables!$AI$5:$AI$9,0))),"")
B62: =IFERROR(INDEX(Entregables!$D$5:$D$9,MATCH(3,Entregables!$AI$5:$AI$9,0)),"") | C62: =IFERROR(INDEX(Entregables!$E$5:$E$9,MATCH(3,Entregables!$AI$5:$AI$9,0)),"") | D62: =IFERROR(INDEX(Entregables!$H$5:$H$9,MATCH(3,Entregables!$AI$5:$AI$9,0)),"") | E62: =IFERROR(INDEX(Entregables!$R$5:$R$9,MATCH(3,Entregables!$AI$5:$AI$9,0)),"") | F62: =IFERROR(INDEX(Entregables!$S$5:$S$9,MATCH(3,Entregables!$AI$5:$AI$9,0)),"") | G62: =IFERROR(INDEX(Entregables!$T$5:$T$9,MATCH(3,Entregables!$AI$5:$AI$9,0)),"") | H62: =IFERROR(INDEX(Entregables!$K$5:$K$9,MATCH(3,Entregables!$AI$5:$AI$9,0)),"") | I62: =IFERROR(IF(INDEX(Entregables!$M$5:$M$9,MATCH(3,Entregables!$AI$5:$AI$9,0))="","",INDEX(Entregables!$M$5:$M$9,MATCH(3,Entregables!$AI$5:$AI$9,0))),"")
B63: =IFERROR(INDEX(Entregables!$D$5:$D$9,MATCH(4,Entregables!$AI$5:$AI$9,0)),"") | C63: =IFERROR(INDEX(Entregables!$E$5:$E$9,MATCH(4,Entregables!$AI$5:$AI$9,0)),"") | D63: =IFERROR(INDEX(Entregables!$H$5:$H$9,MATCH(4,Entregables!$AI$5:$AI$9,0)),"") | E63: =IFERROR(INDEX(Entregables!$R$5:$R$9,MATCH(4,Entregables!$AI$5:$AI$9,0)),"") | F63: =IFERROR(INDEX(Entregables!$S$5:$S$9,MATCH(4,Entregables!$AI$5:$AI$9,0)),"") | G63: =IFERROR(INDEX(Entregables!$T$5:$T$9,MATCH(4,Entregables!$AI$5:$AI$9,0)),"") | H63: =IFERROR(INDEX(Entregables!$K$5:$K$9,MATCH(4,Entregables!$AI$5:$AI$9,0)),"") | I63: =IFERROR(IF(INDEX(Entregables!$M$5:$M$9,MATCH(4,Entregables!$AI$5:$AI$9,0))="","",INDEX(Entregables!$M$5:$M$9,MATCH(4,Entregables!$AI$5:$AI$9,0))),"")
B64: =IFERROR(INDEX(Entregables!$D$5:$D$9,MATCH(5,Entregables!$AI$5:$AI$9,0)),"") | C64: =IFERROR(INDEX(Entregables!$E$5:$E$9,MATCH(5,Entregables!$AI$5:$AI$9,0)),"") | D64: =IFERROR(INDEX(Entregables!$H$5:$H$9,MATCH(5,Entregables!$AI$5:$AI$9,0)),"") | E64: =IFERROR(INDEX(Entregables!$R$5:$R$9,MATCH(5,Entregables!$AI$5:$AI$9,0)),"") | F64: =IFERROR(INDEX(Entregables!$S$5:$S$9,MATCH(5,Entregables!$AI$5:$AI$9,0)),"") | G64: =IFERROR(INDEX(Entregables!$T$5:$T$9,MATCH(5,Entregables!$AI$5:$AI$9,0)),"") | H64: =IFERROR(INDEX(Entregables!$K$5:$K$9,MATCH(5,Entregables!$AI$5:$AI$9,0)),"") | I64: =IFERROR(IF(INDEX(Entregables!$M$5:$M$9,MATCH(5,Entregables!$AI$5:$AI$9,0))="","",INDEX(Entregables!$M$5:$M$9,MATCH(5,Entregables!$AI$5:$AI$9,0))),"")
B66: ="DESEMBOLSOS · TODOS LOS DESEMBOLSOS ("&4&")" -> DESEMBOLSOS · TODOS LOS DESEMBOLSOS (4) | H66: ↑ Índice | I66: ← Panel
B67: Desembolso | C67: Lo habilita | D67: Monto | E67: % convenio | F67: Estado | G67: Siguiente paso | H67: Fecha de pago | I67: Saldo por rendir
B68: =IFERROR(INDEX(Desembolsos!$A$5:$A$8,MATCH(1,Desembolsos!$AB$5:$AB$8,0)),"") -> D1 | C68: =IFERROR(INDEX(Desembolsos!$G$5:$G$8,MATCH(1,Desembolsos!$AB$5:$AB$8,0)),"") -> Producto 1 | D68: =IFERROR(INDEX(Desembolsos!$B$5:$B$8,MATCH(1,Desembolsos!$AB$5:$AB$8,0)),"") -> 141375 | E68: =IFERROR(INDEX(Desembolsos!$C$5:$C$8,MATCH(1,Desembolsos!$AB$5:$AB$8,0)),"") -> 0.3 | F68: =IFERROR(INDEX(Desembolsos!$T$5:$T$8,MATCH(1,Desembolsos!$AB$5:$AB$8,0)),"") -> En conformidad | G68: =IFERROR(INDEX(Desembolsos!$U$5:$U$8,MATCH(1,Desembolsos!$AB$5:$AB$8,0)),"") -> Conseguir la opinión técnica del Componente 2 y las conformidades del Coordinador y de FAO | H68: =IFERROR(IF(INDEX(Desembolsos!$P$5:$P$8,MATCH(1,Desembolsos!$AB$5:$AB$8,0))="","",INDEX(Desembolsos!$P$5:$P$8,MATCH(1,Desembolsos!$AB$5:$AB$8,0))),"") | I68: =IFERROR(INDEX(Desembolsos!$S$5:$S$8,MATCH(1,Desembolsos!$AB$5:$AB$8,0)),"") -> 0
B69: =IFERROR(INDEX(Desembolsos!$A$5:$A$8,MATCH(2,Desembolsos!$AB$5:$AB$8,0)),"") -> D2 | C69: =IFERROR(INDEX(Desembolsos!$G$5:$G$8,MATCH(2,Desembolsos!$AB$5:$AB$8,0)),"") -> Producto 2 (Parte I y Parte II) | D69: =IFERROR(INDEX(Desembolsos!$B$5:$B$8,MATCH(2,Desembolsos!$AB$5:$AB$8,0)),"") -> 141375 | E69: =IFERROR(INDEX(Desembolsos!$C$5:$C$8,MATCH(2,Desembolsos!$AB$5:$AB$8,0)),"") -> 0.3 | F69: =IFERROR(INDEX(Desembolsos!$T$5:$T$8,MATCH(2,Desembolsos!$AB$5:$AB$8,0)),"") -> Pendiente de producto | G69: =IFERROR(INDEX(Desembolsos!$U$5:$U$8,MATCH(2,Desembolsos!$AB$5:$AB$8,0)),"") -> Presentar Producto 2 (Parte I y Parte II) (vence el 30/06/2026) | H69: =IFERROR(IF(INDEX(Desembolsos!$P$5:$P$8,MATCH(2,Desembolsos!$AB$5:$AB$8,0))="","",INDEX(Desembolsos!$P$5:$P$8,MATCH(2,Desembolsos!$AB$5:$AB$8,0))),"") | I69: =IFERROR(INDEX(Desembolsos!$S$5:$S$8,MATCH(2,Desembolsos!$AB$5:$AB$8,0)),"") -> 0
B70: =IFERROR(INDEX(Desembolsos!$A$5:$A$8,MATCH(3,Desembolsos!$AB$5:$AB$8,0)),"") -> D3 | C70: =IFERROR(INDEX(Desembolsos!$G$5:$G$8,MATCH(3,Desembolsos!$AB$5:$AB$8,0)),"") -> Producto 3 | D70: =IFERROR(INDEX(Desembolsos!$B$5:$B$8,MATCH(3,Desembolsos!$AB$5:$AB$8,0)),"") -> 117812 | E70: =IFERROR(INDEX(Desembolsos!$C$5:$C$8,MATCH(3,Desembolsos!$AB$5:$AB$8,0)),"") -> 0.24999894 | F70: =IFERROR(INDEX(Desembolsos!$T$5:$T$8,MATCH(3,Desembolsos!$AB$5:$AB$8,0)),"") -> Pendiente de producto | G70: =IFERROR(INDEX(Desembolsos!$U$5:$U$8,MATCH(3,Desembolsos!$AB$5:$AB$8,0)),"") -> Presentar Producto 3 (vence el 18/12/2026) | H70: =IFERROR(IF(INDEX(Desembolsos!$P$5:$P$8,MATCH(3,Desembolsos!$AB$5:$AB$8,0))="","",INDEX(Desembolsos!$P$5:$P$8,MATCH(3,Desembolsos!$AB$5:$AB$8,0))),"") | I70: =IFERROR(INDEX(Desembolsos!$S$5:$S$8,MATCH(3,Desembolsos!$AB$5:$AB$8,0)),"") -> 0
B71: =IFERROR(INDEX(Desembolsos!$A$5:$A$8,MATCH(4,Desembolsos!$AB$5:$AB$8,0)),"") -> D4 | C71: =IFERROR(INDEX(Desembolsos!$G$5:$G$8,MATCH(4,Desembolsos!$AB$5:$AB$8,0)),"") -> Producto 4 | D71: =IFERROR(INDEX(Desembolsos!$B$5:$B$8,MATCH(4,Desembolsos!$AB$5:$AB$8,0)),"") -> 70688 | E71: =IFERROR(INDEX(Desembolsos!$C$5:$C$8,MATCH(4,Desembolsos!$AB$5:$AB$8,0)),"") -> 0.15000106 | F71: =IFERROR(INDEX(Desembolsos!$T$5:$T$8,MATCH(4,Desembolsos!$AB$5:$AB$8,0)),"") -> Pendiente de producto | G71: =IFERROR(INDEX(Desembolsos!$U$5:$U$8,MATCH(4,Desembolsos!$AB$5:$AB$8,0)),"") -> Presentar Producto 4 (vence el 30/04/2027) | H71: =IFERROR(IF(INDEX(Desembolsos!$P$5:$P$8,MATCH(4,Desembolsos!$AB$5:$AB$8,0))="","",INDEX(Desembolsos!$P$5:$P$8,MATCH(4,Desembolsos!$AB$5:$AB$8,0))),"") | I71: =IFERROR(INDEX(Desembolsos!$S$5:$S$8,MATCH(4,Desembolsos!$AB$5:$AB$8,0)),"") -> 0
B73: ="DESEMBOLSOS · DESEMBOLSADO ("&'Datos gráficos'!$C$35&")" -> DESEMBOLSOS · DESEMBOLSADO (0) | H73: ↑ Índice | I73: ← Panel
B74: Desembolso | C74: Lo habilita | D74: Monto | E74: % convenio | F74: Estado | G74: Siguiente paso | H74: Fecha de pago | I74: Saldo por rendir
B75: =IFERROR(INDEX(Desembolsos!$A$5:$A$8,MATCH(1,Desembolsos!$AC$5:$AC$8,0)),"Ningún desembolso en este estado.") -> Ningún desembolso en este estado. | C75: =IFERROR(INDEX(Desembolsos!$G$5:$G$8,MATCH(1,Desembolsos!$AC$5:$AC$8,0)),"") | D75: =IFERROR(INDEX(Desembolsos!$B$5:$B$8,MATCH(1,Desembolsos!$AC$5:$AC$8,0)),"") | E75: =IFERROR(INDEX(Desembolsos!$C$5:$C$8,MATCH(1,Desembolsos!$AC$5:$AC$8,0)),"") | F75: =IFERROR(INDEX(Desembolsos!$T$5:$T$8,MATCH(1,Desembolsos!$AC$5:$AC$8,0)),"") | G75: =IFERROR(INDEX(Desembolsos!$U$5:$U$8,MATCH(1,Desembolsos!$AC$5:$AC$8,0)),"") | H75: =IFERROR(IF(INDEX(Desembolsos!$P$5:$P$8,MATCH(1,Desembolsos!$AC$5:$AC$8,0))="","",INDEX(Desembolsos!$P$5:$P$8,MATCH(1,Desembolsos!$AC$5:$AC$8,0))),"") | I75: =IFERROR(INDEX(Desembolsos!$S$5:$S$8,MATCH(1,Desembolsos!$AC$5:$AC$8,0)),"")
B76: =IFERROR(INDEX(Desembolsos!$A$5:$A$8,MATCH(2,Desembolsos!$AC$5:$AC$8,0)),"") | C76: =IFERROR(INDEX(Desembolsos!$G$5:$G$8,MATCH(2,Desembolsos!$AC$5:$AC$8,0)),"") | D76: =IFERROR(INDEX(Desembolsos!$B$5:$B$8,MATCH(2,Desembolsos!$AC$5:$AC$8,0)),"") | E76: =IFERROR(INDEX(Desembolsos!$C$5:$C$8,MATCH(2,Desembolsos!$AC$5:$AC$8,0)),"") | F76: =IFERROR(INDEX(Desembolsos!$T$5:$T$8,MATCH(2,Desembolsos!$AC$5:$AC$8,0)),"") | G76: =IFERROR(INDEX(Desembolsos!$U$5:$U$8,MATCH(2,Desembolsos!$AC$5:$AC$8,0)),"") | H76: =IFERROR(IF(INDEX(Desembolsos!$P$5:$P$8,MATCH(2,Desembolsos!$AC$5:$AC$8,0))="","",INDEX(Desembolsos!$P$5:$P$8,MATCH(2,Desembolsos!$AC$5:$AC$8,0))),"") | I76: =IFERROR(INDEX(Desembolsos!$S$5:$S$8,MATCH(2,Desembolsos!$AC$5:$AC$8,0)),"")
B77: =IFERROR(INDEX(Desembolsos!$A$5:$A$8,MATCH(3,Desembolsos!$AC$5:$AC$8,0)),"") | C77: =IFERROR(INDEX(Desembolsos!$G$5:$G$8,MATCH(3,Desembolsos!$AC$5:$AC$8,0)),"") | D77: =IFERROR(INDEX(Desembolsos!$B$5:$B$8,MATCH(3,Desembolsos!$AC$5:$AC$8,0)),"") | E77: =IFERROR(INDEX(Desembolsos!$C$5:$C$8,MATCH(3,Desembolsos!$AC$5:$AC$8,0)),"") | F77: =IFERROR(INDEX(Desembolsos!$T$5:$T$8,MATCH(3,Desembolsos!$AC$5:$AC$8,0)),"") | G77: =IFERROR(INDEX(Desembolsos!$U$5:$U$8,MATCH(3,Desembolsos!$AC$5:$AC$8,0)),"") | H77: =IFERROR(IF(INDEX(Desembolsos!$P$5:$P$8,MATCH(3,Desembolsos!$AC$5:$AC$8,0))="","",INDEX(Desembolsos!$P$5:$P$8,MATCH(3,Desembolsos!$AC$5:$AC$8,0))),"") | I77: =IFERROR(INDEX(Desembolsos!$S$5:$S$8,MATCH(3,Desembolsos!$AC$5:$AC$8,0)),"")
B78: =IFERROR(INDEX(Desembolsos!$A$5:$A$8,MATCH(4,Desembolsos!$AC$5:$AC$8,0)),"") | C78: =IFERROR(INDEX(Desembolsos!$G$5:$G$8,MATCH(4,Desembolsos!$AC$5:$AC$8,0)),"") | D78: =IFERROR(INDEX(Desembolsos!$B$5:$B$8,MATCH(4,Desembolsos!$AC$5:$AC$8,0)),"") | E78: =IFERROR(INDEX(Desembolsos!$C$5:$C$8,MATCH(4,Desembolsos!$AC$5:$AC$8,0)),"") | F78: =IFERROR(INDEX(Desembolsos!$T$5:$T$8,MATCH(4,Desembolsos!$AC$5:$AC$8,0)),"") | G78: =IFERROR(INDEX(Desembolsos!$U$5:$U$8,MATCH(4,Desembolsos!$AC$5:$AC$8,0)),"") | H78: =IFERROR(IF(INDEX(Desembolsos!$P$5:$P$8,MATCH(4,Desembolsos!$AC$5:$AC$8,0))="","",INDEX(Desembolsos!$P$5:$P$8,MATCH(4,Desembolsos!$AC$5:$AC$8,0))),"") | I78: =IFERROR(INDEX(Desembolsos!$S$5:$S$8,MATCH(4,Desembolsos!$AC$5:$AC$8,0)),"")
B80: ="DESEMBOLSOS · LISTO PARA SOLICITAR ("&'Datos gráficos'!$C$36&")" -> DESEMBOLSOS · LISTO PARA SOLICITAR (0) | H80: ↑ Índice | I80: ← Panel
B81: Desembolso | C81: Lo habilita | D81: Monto | E81: % convenio | F81: Estado | G81: Siguiente paso | H81: Fecha de pago | I81: Saldo por rendir
B82: =IFERROR(INDEX(Desembolsos!$A$5:$A$8,MATCH(1,Desembolsos!$AD$5:$AD$8,0)),"Ningún desembolso en este estado.") -> Ningún desembolso en este estado. | C82: =IFERROR(INDEX(Desembolsos!$G$5:$G$8,MATCH(1,Desembolsos!$AD$5:$AD$8,0)),"") | D82: =IFERROR(INDEX(Desembolsos!$B$5:$B$8,MATCH(1,Desembolsos!$AD$5:$AD$8,0)),"") | E82: =IFERROR(INDEX(Desembolsos!$C$5:$C$8,MATCH(1,Desembolsos!$AD$5:$AD$8,0)),"") | F82: =IFERROR(INDEX(Desembolsos!$T$5:$T$8,MATCH(1,Desembolsos!$AD$5:$AD$8,0)),"") | G82: =IFERROR(INDEX(Desembolsos!$U$5:$U$8,MATCH(1,Desembolsos!$AD$5:$AD$8,0)),"") | H82: =IFERROR(IF(INDEX(Desembolsos!$P$5:$P$8,MATCH(1,Desembolsos!$AD$5:$AD$8,0))="","",INDEX(Desembolsos!$P$5:$P$8,MATCH(1,Desembolsos!$AD$5:$AD$8,0))),"") | I82: =IFERROR(INDEX(Desembolsos!$S$5:$S$8,MATCH(1,Desembolsos!$AD$5:$AD$8,0)),"")
B83: =IFERROR(INDEX(Desembolsos!$A$5:$A$8,MATCH(2,Desembolsos!$AD$5:$AD$8,0)),"") | C83: =IFERROR(INDEX(Desembolsos!$G$5:$G$8,MATCH(2,Desembolsos!$AD$5:$AD$8,0)),"") | D83: =IFERROR(INDEX(Desembolsos!$B$5:$B$8,MATCH(2,Desembolsos!$AD$5:$AD$8,0)),"") | E83: =IFERROR(INDEX(Desembolsos!$C$5:$C$8,MATCH(2,Desembolsos!$AD$5:$AD$8,0)),"") | F83: =IFERROR(INDEX(Desembolsos!$T$5:$T$8,MATCH(2,Desembolsos!$AD$5:$AD$8,0)),"") | G83: =IFERROR(INDEX(Desembolsos!$U$5:$U$8,MATCH(2,Desembolsos!$AD$5:$AD$8,0)),"") | H83: =IFERROR(IF(INDEX(Desembolsos!$P$5:$P$8,MATCH(2,Desembolsos!$AD$5:$AD$8,0))="","",INDEX(Desembolsos!$P$5:$P$8,MATCH(2,Desembolsos!$AD$5:$AD$8,0))),"") | I83: =IFERROR(INDEX(Desembolsos!$S$5:$S$8,MATCH(2,Desembolsos!$AD$5:$AD$8,0)),"")
B84: =IFERROR(INDEX(Desembolsos!$A$5:$A$8,MATCH(3,Desembolsos!$AD$5:$AD$8,0)),"") | C84: =IFERROR(INDEX(Desembolsos!$G$5:$G$8,MATCH(3,Desembolsos!$AD$5:$AD$8,0)),"") | D84: =IFERROR(INDEX(Desembolsos!$B$5:$B$8,MATCH(3,Desembolsos!$AD$5:$AD$8,0)),"") | E84: =IFERROR(INDEX(Desembolsos!$C$5:$C$8,MATCH(3,Desembolsos!$AD$5:$AD$8,0)),"") | F84: =IFERROR(INDEX(Desembolsos!$T$5:$T$8,MATCH(3,Desembolsos!$AD$5:$AD$8,0)),"") | G84: =IFERROR(INDEX(Desembolsos!$U$5:$U$8,MATCH(3,Desembolsos!$AD$5:$AD$8,0)),"") | H84: =IFERROR(IF(INDEX(Desembolsos!$P$5:$P$8,MATCH(3,Desembolsos!$AD$5:$AD$8,0))="","",INDEX(Desembolsos!$P$5:$P$8,MATCH(3,Desembolsos!$AD$5:$AD$8,0))),"") | I84: =IFERROR(INDEX(Desembolsos!$S$5:$S$8,MATCH(3,Desembolsos!$AD$5:$AD$8,0)),"")
B85: =IFERROR(INDEX(Desembolsos!$A$5:$A$8,MATCH(4,Desembolsos!$AD$5:$AD$8,0)),"") | C85: =IFERROR(INDEX(Desembolsos!$G$5:$G$8,MATCH(4,Desembolsos!$AD$5:$AD$8,0)),"") | D85: =IFERROR(INDEX(Desembolsos!$B$5:$B$8,MATCH(4,Desembolsos!$AD$5:$AD$8,0)),"") | E85: =IFERROR(INDEX(Desembolsos!$C$5:$C$8,MATCH(4,Desembolsos!$AD$5:$AD$8,0)),"") | F85: =IFERROR(INDEX(Desembolsos!$T$5:$T$8,MATCH(4,Desembolsos!$AD$5:$AD$8,0)),"") | G85: =IFERROR(INDEX(Desembolsos!$U$5:$U$8,MATCH(4,Desembolsos!$AD$5:$AD$8,0)),"") | H85: =IFERROR(IF(INDEX(Desembolsos!$P$5:$P$8,MATCH(4,Desembolsos!$AD$5:$AD$8,0))="","",INDEX(Desembolsos!$P$5:$P$8,MATCH(4,Desembolsos!$AD$5:$AD$8,0))),"") | I85: =IFERROR(INDEX(Desembolsos!$S$5:$S$8,MATCH(4,Desembolsos!$AD$5:$AD$8,0)),"")
B87: ="DESEMBOLSOS · FALTA RENDICIÓN ("&'Datos gráficos'!$C$37&")" -> DESEMBOLSOS · FALTA RENDICIÓN (0) | H87: ↑ Índice | I87: ← Panel
B88: Desembolso | C88: Lo habilita | D88: Monto | E88: % convenio | F88: Estado | G88: Siguiente paso | H88: Fecha de pago | I88: Saldo por rendir
B89: =IFERROR(INDEX(Desembolsos!$A$5:$A$8,MATCH(1,Desembolsos!$AE$5:$AE$8,0)),"Ningún desembolso en este estado.") -> Ningún desembolso en este estado. | C89: =IFERROR(INDEX(Desembolsos!$G$5:$G$8,MATCH(1,Desembolsos!$AE$5:$AE$8,0)),"") | D89: =IFERROR(INDEX(Desembolsos!$B$5:$B$8,MATCH(1,Desembolsos!$AE$5:$AE$8,0)),"") | E89: =IFERROR(INDEX(Desembolsos!$C$5:$C$8,MATCH(1,Desembolsos!$AE$5:$AE$8,0)),"") | F89: =IFERROR(INDEX(Desembolsos!$T$5:$T$8,MATCH(1,Desembolsos!$AE$5:$AE$8,0)),"") | G89: =IFERROR(INDEX(Desembolsos!$U$5:$U$8,MATCH(1,Desembolsos!$AE$5:$AE$8,0)),"") | H89: =IFERROR(IF(INDEX(Desembolsos!$P$5:$P$8,MATCH(1,Desembolsos!$AE$5:$AE$8,0))="","",INDEX(Desembolsos!$P$5:$P$8,MATCH(1,Desembolsos!$AE$5:$AE$8,0))),"") | I89: =IFERROR(INDEX(Desembolsos!$S$5:$S$8,MATCH(1,Desembolsos!$AE$5:$AE$8,0)),"")
B90: =IFERROR(INDEX(Desembolsos!$A$5:$A$8,MATCH(2,Desembolsos!$AE$5:$AE$8,0)),"") | C90: =IFERROR(INDEX(Desembolsos!$G$5:$G$8,MATCH(2,Desembolsos!$AE$5:$AE$8,0)),"") | D90: =IFERROR(INDEX(Desembolsos!$B$5:$B$8,MATCH(2,Desembolsos!$AE$5:$AE$8,0)),"") | E90: =IFERROR(INDEX(Desembolsos!$C$5:$C$8,MATCH(2,Desembolsos!$AE$5:$AE$8,0)),"") | F90: =IFERROR(INDEX(Desembolsos!$T$5:$T$8,MATCH(2,Desembolsos!$AE$5:$AE$8,0)),"") | G90: =IFERROR(INDEX(Desembolsos!$U$5:$U$8,MATCH(2,Desembolsos!$AE$5:$AE$8,0)),"") | H90: =IFERROR(IF(INDEX(Desembolsos!$P$5:$P$8,MATCH(2,Desembolsos!$AE$5:$AE$8,0))="","",INDEX(Desembolsos!$P$5:$P$8,MATCH(2,Desembolsos!$AE$5:$AE$8,0))),"") | I90: =IFERROR(INDEX(Desembolsos!$S$5:$S$8,MATCH(2,Desembolsos!$AE$5:$AE$8,0)),"")
B91: =IFERROR(INDEX(Desembolsos!$A$5:$A$8,MATCH(3,Desembolsos!$AE$5:$AE$8,0)),"") | C91: =IFERROR(INDEX(Desembolsos!$G$5:$G$8,MATCH(3,Desembolsos!$AE$5:$AE$8,0)),"") | D91: =IFERROR(INDEX(Desembolsos!$B$5:$B$8,MATCH(3,Desembolsos!$AE$5:$AE$8,0)),"") | E91: =IFERROR(INDEX(Desembolsos!$C$5:$C$8,MATCH(3,Desembolsos!$AE$5:$AE$8,0)),"") | F91: =IFERROR(INDEX(Desembolsos!$T$5:$T$8,MATCH(3,Desembolsos!$AE$5:$AE$8,0)),"") | G91: =IFERROR(INDEX(Desembolsos!$U$5:$U$8,MATCH(3,Desembolsos!$AE$5:$AE$8,0)),"") | H91: =IFERROR(IF(INDEX(Desembolsos!$P$5:$P$8,MATCH(3,Desembolsos!$AE$5:$AE$8,0))="","",INDEX(Desembolsos!$P$5:$P$8,MATCH(3,Desembolsos!$AE$5:$AE$8,0))),"") | I91: =IFERROR(INDEX(Desembolsos!$S$5:$S$8,MATCH(3,Desembolsos!$AE$5:$AE$8,0)),"")
B92: =IFERROR(INDEX(Desembolsos!$A$5:$A$8,MATCH(4,Desembolsos!$AE$5:$AE$8,0)),"") | C92: =IFERROR(INDEX(Desembolsos!$G$5:$G$8,MATCH(4,Desembolsos!$AE$5:$AE$8,0)),"") | D92: =IFERROR(INDEX(Desembolsos!$B$5:$B$8,MATCH(4,Desembolsos!$AE$5:$AE$8,0)),"") | E92: =IFERROR(INDEX(Desembolsos!$C$5:$C$8,MATCH(4,Desembolsos!$AE$5:$AE$8,0)),"") | F92: =IFERROR(INDEX(Desembolsos!$T$5:$T$8,MATCH(4,Desembolsos!$AE$5:$AE$8,0)),"") | G92: =IFERROR(INDEX(Desembolsos!$U$5:$U$8,MATCH(4,Desembolsos!$AE$5:$AE$8,0)),"") | H92: =IFERROR(IF(INDEX(Desembolsos!$P$5:$P$8,MATCH(4,Desembolsos!$AE$5:$AE$8,0))="","",INDEX(Desembolsos!$P$5:$P$8,MATCH(4,Desembolsos!$AE$5:$AE$8,0))),"") | I92: =IFERROR(INDEX(Desembolsos!$S$5:$S$8,MATCH(4,Desembolsos!$AE$5:$AE$8,0)),"")
B94: ="DESEMBOLSOS · EN CONFORMIDAD ("&'Datos gráficos'!$C$38&")" -> DESEMBOLSOS · EN CONFORMIDAD (1) | H94: ↑ Índice | I94: ← Panel
B95: Desembolso | C95: Lo habilita | D95: Monto | E95: % convenio | F95: Estado | G95: Siguiente paso | H95: Fecha de pago | I95: Saldo por rendir
B96: =IFERROR(INDEX(Desembolsos!$A$5:$A$8,MATCH(1,Desembolsos!$AF$5:$AF$8,0)),"Ningún desembolso en este estado.") -> D1 | C96: =IFERROR(INDEX(Desembolsos!$G$5:$G$8,MATCH(1,Desembolsos!$AF$5:$AF$8,0)),"") -> Producto 1 | D96: =IFERROR(INDEX(Desembolsos!$B$5:$B$8,MATCH(1,Desembolsos!$AF$5:$AF$8,0)),"") -> 141375 | E96: =IFERROR(INDEX(Desembolsos!$C$5:$C$8,MATCH(1,Desembolsos!$AF$5:$AF$8,0)),"") -> 0.3 | F96: =IFERROR(INDEX(Desembolsos!$T$5:$T$8,MATCH(1,Desembolsos!$AF$5:$AF$8,0)),"") -> En conformidad | G96: =IFERROR(INDEX(Desembolsos!$U$5:$U$8,MATCH(1,Desembolsos!$AF$5:$AF$8,0)),"") -> Conseguir la opinión técnica del Componente 2 y las conformidades del Coordinador y de FAO | H96: =IFERROR(IF(INDEX(Desembolsos!$P$5:$P$8,MATCH(1,Desembolsos!$AF$5:$AF$8,0))="","",INDEX(Desembolsos!$P$5:$P$8,MATCH(1,Desembolsos!$AF$5:$AF$8,0))),"") | I96: =IFERROR(INDEX(Desembolsos!$S$5:$S$8,MATCH(1,Desembolsos!$AF$5:$AF$8,0)),"") -> 0
B97: =IFERROR(INDEX(Desembolsos!$A$5:$A$8,MATCH(2,Desembolsos!$AF$5:$AF$8,0)),"") | C97: =IFERROR(INDEX(Desembolsos!$G$5:$G$8,MATCH(2,Desembolsos!$AF$5:$AF$8,0)),"") | D97: =IFERROR(INDEX(Desembolsos!$B$5:$B$8,MATCH(2,Desembolsos!$AF$5:$AF$8,0)),"") | E97: =IFERROR(INDEX(Desembolsos!$C$5:$C$8,MATCH(2,Desembolsos!$AF$5:$AF$8,0)),"") | F97: =IFERROR(INDEX(Desembolsos!$T$5:$T$8,MATCH(2,Desembolsos!$AF$5:$AF$8,0)),"") | G97: =IFERROR(INDEX(Desembolsos!$U$5:$U$8,MATCH(2,Desembolsos!$AF$5:$AF$8,0)),"") | H97: =IFERROR(IF(INDEX(Desembolsos!$P$5:$P$8,MATCH(2,Desembolsos!$AF$5:$AF$8,0))="","",INDEX(Desembolsos!$P$5:$P$8,MATCH(2,Desembolsos!$AF$5:$AF$8,0))),"") | I97: =IFERROR(INDEX(Desembolsos!$S$5:$S$8,MATCH(2,Desembolsos!$AF$5:$AF$8,0)),"")
B98: =IFERROR(INDEX(Desembolsos!$A$5:$A$8,MATCH(3,Desembolsos!$AF$5:$AF$8,0)),"") | C98: =IFERROR(INDEX(Desembolsos!$G$5:$G$8,MATCH(3,Desembolsos!$AF$5:$AF$8,0)),"") | D98: =IFERROR(INDEX(Desembolsos!$B$5:$B$8,MATCH(3,Desembolsos!$AF$5:$AF$8,0)),"") | E98: =IFERROR(INDEX(Desembolsos!$C$5:$C$8,MATCH(3,Desembolsos!$AF$5:$AF$8,0)),"") | F98: =IFERROR(INDEX(Desembolsos!$T$5:$T$8,MATCH(3,Desembolsos!$AF$5:$AF$8,0)),"") | G98: =IFERROR(INDEX(Desembolsos!$U$5:$U$8,MATCH(3,Desembolsos!$AF$5:$AF$8,0)),"") | H98: =IFERROR(IF(INDEX(Desembolsos!$P$5:$P$8,MATCH(3,Desembolsos!$AF$5:$AF$8,0))="","",INDEX(Desembolsos!$P$5:$P$8,MATCH(3,Desembolsos!$AF$5:$AF$8,0))),"") | I98: =IFERROR(INDEX(Desembolsos!$S$5:$S$8,MATCH(3,Desembolsos!$AF$5:$AF$8,0)),"")
B99: =IFERROR(INDEX(Desembolsos!$A$5:$A$8,MATCH(4,Desembolsos!$AF$5:$AF$8,0)),"") | C99: =IFERROR(INDEX(Desembolsos!$G$5:$G$8,MATCH(4,Desembolsos!$AF$5:$AF$8,0)),"") | D99: =IFERROR(INDEX(Desembolsos!$B$5:$B$8,MATCH(4,Desembolsos!$AF$5:$AF$8,0)),"") | E99: =IFERROR(INDEX(Desembolsos!$C$5:$C$8,MATCH(4,Desembolsos!$AF$5:$AF$8,0)),"") | F99: =IFERROR(INDEX(Desembolsos!$T$5:$T$8,MATCH(4,Desembolsos!$AF$5:$AF$8,0)),"") | G99: =IFERROR(INDEX(Desembolsos!$U$5:$U$8,MATCH(4,Desembolsos!$AF$5:$AF$8,0)),"") | H99: =IFERROR(IF(INDEX(Desembolsos!$P$5:$P$8,MATCH(4,Desembolsos!$AF$5:$AF$8,0))="","",INDEX(Desembolsos!$P$5:$P$8,MATCH(4,Desembolsos!$AF$5:$AF$8,0))),"") | I99: =IFERROR(INDEX(Desembolsos!$S$5:$S$8,MATCH(4,Desembolsos!$AF$5:$AF$8,0)),"")
B101: ="DESEMBOLSOS · PENDIENTE DE PRODUCTO ("&'Datos gráficos'!$C$39&")" -> DESEMBOLSOS · PENDIENTE DE PRODUCTO (3) | H101: ↑ Índice | I101: ← Panel
B102: Desembolso | C102: Lo habilita | D102: Monto | E102: % convenio | F102: Estado | G102: Siguiente paso | H102: Fecha de pago | I102: Saldo por rendir
B103: =IFERROR(INDEX(Desembolsos!$A$5:$A$8,MATCH(1,Desembolsos!$AG$5:$AG$8,0)),"Ningún desembolso en este estado.") -> D2 | C103: =IFERROR(INDEX(Desembolsos!$G$5:$G$8,MATCH(1,Desembolsos!$AG$5:$AG$8,0)),"") -> Producto 2 (Parte I y Parte II) | D103: =IFERROR(INDEX(Desembolsos!$B$5:$B$8,MATCH(1,Desembolsos!$AG$5:$AG$8,0)),"") -> 141375 | E103: =IFERROR(INDEX(Desembolsos!$C$5:$C$8,MATCH(1,Desembolsos!$AG$5:$AG$8,0)),"") -> 0.3 | F103: =IFERROR(INDEX(Desembolsos!$T$5:$T$8,MATCH(1,Desembolsos!$AG$5:$AG$8,0)),"") -> Pendiente de producto | G103: =IFERROR(INDEX(Desembolsos!$U$5:$U$8,MATCH(1,Desembolsos!$AG$5:$AG$8,0)),"") -> Presentar Producto 2 (Parte I y Parte II) (vence el 30/06/2026) | H103: =IFERROR(IF(INDEX(Desembolsos!$P$5:$P$8,MATCH(1,Desembolsos!$AG$5:$AG$8,0))="","",INDEX(Desembolsos!$P$5:$P$8,MATCH(1,Desembolsos!$AG$5:$AG$8,0))),"") | I103: =IFERROR(INDEX(Desembolsos!$S$5:$S$8,MATCH(1,Desembolsos!$AG$5:$AG$8,0)),"") -> 0
B104: =IFERROR(INDEX(Desembolsos!$A$5:$A$8,MATCH(2,Desembolsos!$AG$5:$AG$8,0)),"") -> D3 | C104: =IFERROR(INDEX(Desembolsos!$G$5:$G$8,MATCH(2,Desembolsos!$AG$5:$AG$8,0)),"") -> Producto 3 | D104: =IFERROR(INDEX(Desembolsos!$B$5:$B$8,MATCH(2,Desembolsos!$AG$5:$AG$8,0)),"") -> 117812 | E104: =IFERROR(INDEX(Desembolsos!$C$5:$C$8,MATCH(2,Desembolsos!$AG$5:$AG$8,0)),"") -> 0.24999894 | F104: =IFERROR(INDEX(Desembolsos!$T$5:$T$8,MATCH(2,Desembolsos!$AG$5:$AG$8,0)),"") -> Pendiente de producto | G104: =IFERROR(INDEX(Desembolsos!$U$5:$U$8,MATCH(2,Desembolsos!$AG$5:$AG$8,0)),"") -> Presentar Producto 3 (vence el 18/12/2026) | H104: =IFERROR(IF(INDEX(Desembolsos!$P$5:$P$8,MATCH(2,Desembolsos!$AG$5:$AG$8,0))="","",INDEX(Desembolsos!$P$5:$P$8,MATCH(2,Desembolsos!$AG$5:$AG$8,0))),"") | I104: =IFERROR(INDEX(Desembolsos!$S$5:$S$8,MATCH(2,Desembolsos!$AG$5:$AG$8,0)),"") -> 0
B105: =IFERROR(INDEX(Desembolsos!$A$5:$A$8,MATCH(3,Desembolsos!$AG$5:$AG$8,0)),"") -> D4 | C105: =IFERROR(INDEX(Desembolsos!$G$5:$G$8,MATCH(3,Desembolsos!$AG$5:$AG$8,0)),"") -> Producto 4 | D105: =IFERROR(INDEX(Desembolsos!$B$5:$B$8,MATCH(3,Desembolsos!$AG$5:$AG$8,0)),"") -> 70688 | E105: =IFERROR(INDEX(Desembolsos!$C$5:$C$8,MATCH(3,Desembolsos!$AG$5:$AG$8,0)),"") -> 0.15000106 | F105: =IFERROR(INDEX(Desembolsos!$T$5:$T$8,MATCH(3,Desembolsos!$AG$5:$AG$8,0)),"") -> Pendiente de producto | G105: =IFERROR(INDEX(Desembolsos!$U$5:$U$8,MATCH(3,Desembolsos!$AG$5:$AG$8,0)),"") -> Presentar Producto 4 (vence el 30/04/2027) | H105: =IFERROR(IF(INDEX(Desembolsos!$P$5:$P$8,MATCH(3,Desembolsos!$AG$5:$AG$8,0))="","",INDEX(Desembolsos!$P$5:$P$8,MATCH(3,Desembolsos!$AG$5:$AG$8,0))),"") | I105: =IFERROR(INDEX(Desembolsos!$S$5:$S$8,MATCH(3,Desembolsos!$AG$5:$AG$8,0)),"") -> 0
B106: =IFERROR(INDEX(Desembolsos!$A$5:$A$8,MATCH(4,Desembolsos!$AG$5:$AG$8,0)),"") | C106: =IFERROR(INDEX(Desembolsos!$G$5:$G$8,MATCH(4,Desembolsos!$AG$5:$AG$8,0)),"") | D106: =IFERROR(INDEX(Desembolsos!$B$5:$B$8,MATCH(4,Desembolsos!$AG$5:$AG$8,0)),"") | E106: =IFERROR(INDEX(Desembolsos!$C$5:$C$8,MATCH(4,Desembolsos!$AG$5:$AG$8,0)),"") | F106: =IFERROR(INDEX(Desembolsos!$T$5:$T$8,MATCH(4,Desembolsos!$AG$5:$AG$8,0)),"") | G106: =IFERROR(INDEX(Desembolsos!$U$5:$U$8,MATCH(4,Desembolsos!$AG$5:$AG$8,0)),"") | H106: =IFERROR(IF(INDEX(Desembolsos!$P$5:$P$8,MATCH(4,Desembolsos!$AG$5:$AG$8,0))="","",INDEX(Desembolsos!$P$5:$P$8,MATCH(4,Desembolsos!$AG$5:$AG$8,0))),"") | I106: =IFERROR(INDEX(Desembolsos!$S$5:$S$8,MATCH(4,Desembolsos!$AG$5:$AG$8,0)),"")

Sheet Línea de tiempo
B1: ← Volver al Panel
B2: Línea de tiempo semanal (plazos de la Adenda N.° 01)
B3: Cada celda es una semana (empieza en lunes). El color sigue el estado de cada producto; la columna amarilla y ▼ marcan la semana de la fecha de referencia.
F5: =F6 -> 45943 | G5: =IF(DAY(G6)<=7,G6,"") | H5: =IF(DAY(H6)<=7,H6,"") | I5: =IF(DAY(I6)<=7,I6,"") -> 45964 | J5: =IF(DAY(J6)<=7,J6,"") | K5: =IF(DAY(K6)<=7,K6,"") | L5: =IF(DAY(L6)<=7,L6,"") | M5: =IF(DAY(M6)<=7,M6,"") -> 45992 | N5: =IF(DAY(N6)<=7,N6,"") | ... CS5: =IF(DAY(CS6)<=7,CS6,"")
F6: =Inicio-WEEKDAY(Inicio,3) -> 45943 | G6: =F6+7 -> 45950 | H6: =G6+7 -> 45957 | I6: =H6+7 -> 45964 | J6: =I6+7 -> 45971 | K6: =J6+7 -> 45978 | L6: =K6+7 -> 45985 | M6: =L6+7 -> 45992 | N6: =M6+7 -> 45999 | ... CS6: =CR6+7 -> 46580
B7: Producto | C7: Inicio | D7: Fecha límite | E7: Estado | F7: =IF(AND(FechaRef>=F6,FechaRef<F6+7),"▼","") | G7: =IF(AND(FechaRef>=G6,FechaRef<G6+7),"▼","") | H7: =IF(AND(FechaRef>=H6,FechaRef<H6+7),"▼","") | I7: =IF(AND(FechaRef>=I6,FechaRef<I6+7),"▼","") | J7: =IF(AND(FechaRef>=J6,FechaRef<J6+7),"▼","") | K7: =IF(AND(FechaRef>=K6,FechaRef<K6+7),"▼","") | L7: =IF(AND(FechaRef>=L6,FechaRef<L6+7),"▼","") | M7: =IF(AND(FechaRef>=M6,FechaRef<M6+7),"▼","") | ... CS7: =IF(AND(FechaRef>=CS6,FechaRef<CS6+7),"▼","")
B8: =Entregables!D5 -> Producto 1 | C8: =Entregables!G5 -> 45946 | D8: =Entregables!H5 -> 46011 | E8: =Entregables!S5 -> En revisión
B9: =Entregables!D6 -> Producto 2 · Parte I | C9: =Entregables!G6 -> 46012 | D9: =Entregables!H6 -> 46142 | E9: =Entregables!S6 -> Vencido
B10: =Entregables!D7 -> Producto 2 · Parte II | C10: =Entregables!G7 -> 46143 | D10: =Entregables!H7 -> 46203 | E10: =Entregables!S7 -> Vencido
B11: =Entregables!D8 -> Producto 3 | C11: =Entregables!G8 -> 46204 | D11: =Entregables!H8 -> 46374 | E11: =Entregables!S8 -> Por entregar
B12: =Entregables!D9 -> Producto 4 | C12: =Entregables!G9 -> 46375 | D12: =Entregables!H9 -> 46507 | E12: =Entregables!S9 -> Por entregar
B13: Cierre del convenio | C13: =Entregables!H9+1 -> 46508 | D13: =Cierre -> 46535 | E13: Cierre
B15: Leyenda
C16: Por entregar
C17: Por vencer
C18: Vencido
C19: En revisión
C20: Observado
C21: Aprobado
C22: Cierre del convenio
C23: Semana de referencia

Sheet Comparativo
B1: ← Volver al Panel
B2: Comparativo: convenio original frente a la Adenda N.° 01
B3: Cómo cambiaron los plazos de los productos y por qué las fechas de pago de la cláusula 9.1 ya no coinciden con los entregables.
B5: 1. Plazos de los productos: convenio original y Adenda N.° 01
B6: Producto | C6: Cláusula 6 original (días) | D6: Fecha original | E6: Anexo I y cl. 9.1 (días) | F6: Fecha Anexo I | G6: Adenda N.° 01 (días) | H6: Fecha vigente | I6: Prórroga (días)
B7: Producto 1 | C7: =Entregables!V5 -> 15 | D7: =Inicio+C7 -> 45961 | E7: 15 | F7: =Inicio+E7 -> 45961 | G7: =Entregables!F5 -> 65 | H7: =Inicio+G7 -> 46011 | I7: =G7-C7 -> 50
B8: Producto 2 · Parte I | C8: =Entregables!V6 -> 180 | D8: =Inicio+C8 -> 46126 | E8: 120 | F8: =Inicio+E8 -> 46066 | G8: =Entregables!F6 -> 196 | H8: =Inicio+G8 -> 46142 | I8: =G8-C8 -> 16
B9: Producto 2 · Parte II | C9: =Entregables!V7 -> 180 | D9: =Inicio+C9 -> 46126 | E9: 120 | F9: =Inicio+E9 -> 46066 | G9: =Entregables!F7 -> 257 | H9: =Inicio+G9 -> 46203 | I9: =G9-C9 -> 77
B10: Producto 3 | C10: =Entregables!V8 -> 360 | D10: =Inicio+C10 -> 46306 | E10: 240 | F10: =Inicio+E10 -> 46186 | G10: =Entregables!F8 -> 428 | H10: =Inicio+G10 -> 46374 | I10: =G10-C10 -> 68
B11: Producto 4 | C11: =Entregables!V9 -> 540 | D11: =Inicio+C11 -> 46486 | E11: 495 | F11: =Inicio+E11 -> 46441 | G11: =Entregables!F9 -> 561 | H11: =Inicio+G11 -> 46507 | I11: =G11-C11 -> 21
B12: Fin del convenio | C12: =FinOriginal -> 540 | D12: =Inicio+C12 -> 46486 | E12: =FinOriginal -> 540 | F12: =Inicio+E12 -> 46486 | G12: =DiasConvenio -> 589 | H12: =Inicio+G12 -> 46535 | I12: =G12-C12 -> 49
B13: En el convenio original el Producto 2 era un solo entregable (día 180); la Adenda lo divide en Parte I (día 196) y Parte II (día 257).
B15: 2. Cada pago frente al entregable que lo habilita
B16: Desembolso | C16: Monto (S/) | D16: Fecha según 9.1 | E16: Producto que lo habilita | F16: Fecha límite vigente | G16: Diferencia (días) | H16: Estado del pago
B17: ="Desembolso "&1 -> Desembolso 1 | C17: =Desembolsos!B5 -> 141375 | D17: =Desembolsos!F5 -> 45961 | E17: =IF(Desembolsos!H5="P2-II","Producto 2 completo (Parte II)",Desembolsos!G5) -> Producto 1 | F17: =Desembolsos!I5 -> 46011 | G17: =Desembolsos!J5 -> 50 | H17: =Desembolsos!T5 -> En conformidad
B18: ="Desembolso "&2 -> Desembolso 2 | C18: =Desembolsos!B6 -> 141375 | D18: =Desembolsos!F6 -> 46066 | E18: =IF(Desembolsos!H6="P2-II","Producto 2 completo (Parte II)",Desembolsos!G6) -> Producto 2 completo (Parte II) | F18: =Desembolsos!I6 -> 46203 | G18: =Desembolsos!J6 -> 137 | H18: =Desembolsos!T6 -> Pendiente de producto
B19: ="Desembolso "&3 -> Desembolso 3 | C19: =Desembolsos!B7 -> 117812 | D19: =Desembolsos!F7 -> 46186 | E19: =IF(Desembolsos!H7="P2-II","Producto 2 completo (Parte II)",Desembolsos!G7) -> Producto 3 | F19: =Desembolsos!I7 -> 46374 | G19: =Desembolsos!J7 -> 188 | H19: =Desembolsos!T7 -> Pendiente de producto
B20: ="Desembolso "&4 -> Desembolso 4 | C20: =Desembolsos!B8 -> 70688 | D20: =Desembolsos!F8 -> Al presentar P4 | E20: =IF(Desembolsos!H8="P2-II","Producto 2 completo (Parte II)",Desembolsos!G8) -> Producto 4 | F20: =Desembolsos!I8 -> 46507 | G20: =Desembolsos!J8 -> 0 | H20: =Desembolsos!T8 -> Pendiente de producto
B21: ="Las fechas de 9.1 quedan entre "&_xlfn.MINIFS(G17:G20,G17:G20,">0")&" y "&MAX(G17:G20)&" días antes de los entregables vigentes. Conviene actualizarlas por acta (cl. 8.5) o adenda (cl. 16.1)." -> Las fechas de 9.1 quedan entre 50 y 188 días antes de los entregables vigentes. Conviene actualizarlas por acta (cl. 8.5) o adenda (cl. 16.1).
B23: 3. Reparto del pago: cláusula 9.1 frente a los porcentajes de la Adenda
B24: Etapa | C24: Cláusula 9.1 | D24: Acumulado 9.1 | E24: Adenda (tabla 1) | F24: Acumulado Adenda | G24: Diferencia (puntos) | H24: Diferencia en S/
B25: Producto 1 | C25: =Desembolsos!D5 -> 0.3 | D25: =SUM($C$25:C25) -> 0.3 | E25: =Entregables!J5 -> 0.3 | F25: =SUM($E$25:E25) -> 0.3 | G25: =(E25-C25)*100 -> 0 | H25: =(E25-C25)*TotalCARE -> 0
B26: Producto 2 (Partes I y II) | C26: =Desembolsos!D6 -> 0.3 | D26: =SUM($C$25:C26) -> 0.6 | E26: =Entregables!J6+Entregables!J7 -> 0.35 | F26: =SUM($E$25:E26) -> 0.65 | G26: =(E26-C26)*100 -> 5 | H26: =(E26-C26)*TotalCARE -> 23562.5
B27: Producto 3 | C27: =Desembolsos!D7 -> 0.25 | D27: =SUM($C$25:C27) -> 0.85 | E27: =Entregables!J8 -> 0.2 | F27: =SUM($E$25:E27) -> 0.85 | G27: =(E27-C27)*100 -> -5 | H27: =(E27-C27)*TotalCARE -> -23562.5
B28: Producto 4 | C28: =Desembolsos!D8 -> 0.15 | D28: =SUM($C$25:C28) -> 1 | E28: =Entregables!J9 -> 0.15 | F28: =SUM($E$25:E28) -> 1 | G28: =(E28-C28)*100 -> 0 | H28: =(E28-C28)*TotalCARE -> 0
B30: 4. Vigencia del convenio
B31: Concepto | C31: Convenio original | E31: Adenda N.° 01 | G31: Diferencia
B32: Duración | C32: 18 meses | E32: 19 meses y 19 días
B33: Desde | C33: =Inicio -> 45946 | E33: =Inicio -> 45946
B34: Hasta | C34: =Inicio+FinOriginal -> 46486 | E34: =Cierre -> 46535
B35: Días totales | C35: =FinOriginal -> 540 | E35: =DiasConvenio -> 589 | G35: =E35-C35 -> 49

Sheet Paso a paso
B1: ← Volver al Panel
B2: Paso a paso y significado de cada estado
B3: Cómo se arma el cronograma, qué significa cada botón y cómo se llega a un desembolso.
B5: Qué significa cada botón
C6: Estado | D6: Cuándo aparece | E6: Qué hacer
C7: Por entregar | D7: El producto no se ha marcado como entregado y faltan más días que el aviso elegido. | E7: Planificar la entrega.
C8: Por vencer | D8: Faltan menos días que el aviso (15 a 90 días) para la fecha límite de la Adenda. | E8: Priorizar y preparar el producto.
C9: Vencido | D9: Pasó la fecha límite y no se marcó como entregado. | E9: Confirmar si se entregó; si no, comunicar a la UGP.
C10: En revisión | D10: Marcado como entregado; la UGP (10 días hábiles) y FAO (7 días hábiles) revisan. | E10: Hacer seguimiento a la conformidad.
C11: Observado | D11: La UGP o FAO hicieron observaciones (revisión = Observado). | E11: Subsanar en 7 días calendario (+5 con pedido escrito).
C12: Aprobado | D12: Revisión = Conforme: opinión técnica, conformidad del Coordinador y de FAO. | E12: Revisar si el desembolso ya puede solicitarse.
C13: Pendiente de producto | D13: Desembolso cuyo producto aún no se presenta. | E13: Presentar el producto.
C14: En conformidad | D14: Producto presentado, pero aún no aprobado. | E14: Conseguir las conformidades.
C15: Falta rendición | D15: Producto aprobado, pero no se cumple la rendición previa (70 % / 100 %). | E15: Rendir con el Formato R-1 y comprobantes (Anexo II).
C16: Listo para solicitar | D16: Producto aprobado y rendición previa cumplida. | E16: La UGP pide el desembolso por escrito a Profonanpe (cl. 9.3).
C17: Desembolsado | D17: Se marcó el pago como recibido. | E17: Registrar lo que se va rindiendo.
B19: Cómo se arma este cronograma
B20: N° | C20: Paso | D20: Detalle | E20: Plazo
B21: 1 | C21: Se toma la fecha base | D21: El convenio corre desde el 16/10/2025 (cláusula 4.1, ratificada por la Adenda). Todos los plazos se cuentan desde ese día.
B22: 2 | C22: Se suman los días de la Adenda | D22: La Adenda N.° 01 fija 65, 196, 257, 428 y 561 días (antes 15, 180, 360 y 540). Ej.: 16/10/2025 + 65 días = 20/12/2025.
B23: 3 | C23: Se calcula la ventana de trabajo | D23: Cada producto empieza el día siguiente al anterior y termina en su fecha límite.
B24: 4 | C24: Se asigna el estado | D24: Según la fecha de referencia, los días de aviso y lo que registres (entrega y revisión).
B25: 5 | C25: Se cruza con los desembolsos | D25: Cada pago se enlaza con su producto y con la rendición previa exigida en la cláusula 9.1.
B27: Cómo se llega a un desembolso
B28: N° | C28: Paso | D28: Detalle | E28: Plazo
B29: 1 | C29: CARE entrega el producto a la UGP del proyecto ASL2 | D29: Todo informe se presenta primero a la UGP (cláusula 11.1).
B30: 2 | C30: La UGP revisa y puede observar | D30: Cláusula 8.1. | E30: Hasta 10 días hábiles
B31: 3 | C31: CARE subsana las observaciones | D31: Cláusula 8.1. La UGP responde el pedido de ampliación en 3 días. | E31: 7 días calendario (+5)
B32: 4 | C32: FAO da su conformidad técnica a los productos clave | D32: Productos marcados con (*) (cl. 8.2). Observaciones de FAO: 5 días hábiles para resolverlas. | E32: Hasta 7 días hábiles
B33: 5 | C33: Se reúnen las conformidades internas | D33: Opinión técnica del Componente 2 y conformidad de la Coordinación Técnica (cl. 11.2).
B34: 6 | C34: CARE rinde el pago anterior | D34: Al menos el 70 % del desembolso previo (y el 100 % del penúltimo), con el Formato R-1 y comprobantes (Anexo II), más el informe de recursos financiados.
B35: 7 | C35: La UGP pide el desembolso por escrito a Profonanpe | D35: Cláusula 9.3, con conformidad del Coordinador Nacional.
B36: 8 | C36: Profonanpe transfiere a la cuenta exclusiva de CARE | D36: Cuenta del Formato S-03 (cl. 5.2.2). El convenio no fija un plazo para transferir. | E36: Sin plazo fijado
B37: 9 | C37: Rendición del saldo final | D37: El saldo del 4.º desembolso se rinde junto con el informe final (cl. 9.2). | E37: Hasta 10 días

Sheet Dudas
B1: ← Volver al Panel
B2: Dudas por aclarar con Profonanpe
B3: Puntos donde los documentos se contradicen o no dicen cuál prevalece. Resolverlos por escrito: acta (cl. 8.5) o adenda (cl. 16.1).
B4: N° | C4: Tema | D4: Detalle | E4: Pregunta a Profonanpe | F4: Estado | G4: Responsable | H4: Fecha de respuesta | I4: Respuesta / acuerdo
B5: 1 | C5: La cláusula 9.1 no se actualizó con la Adenda | D5: Sigue diciendo que se paga a los 15, 120 y 240 días, y la Adenda movió los productos a los días 65, 196, 257 y 428. Esas fechas de pago ya no coinciden con ningún entregable vigente. | E5: ¿Qué fecha o condición rige para cada desembolso? | F5: Pendiente
B6: 2 | C6: Porcentajes de la Adenda frente a los pagos de 9.1 | D6: La tabla 1 de la Adenda reparte 30, 20, 15, 20 y 15 %. La cláusula 9.1 paga 30, 30, 25 y 15 %. En el Producto 2 hay 5 puntos de diferencia (≈ S/ 23,562.50). | E6: ¿Se mantienen los 4 pagos de la cláusula 9.1 o se pagará según la tabla de la Adenda? | F6: Pendiente
B7: 3 | C7: El Producto 2 ahora tiene dos fechas | D7: La Adenda lo divide en Parte I (30/04/2026) y Parte II (30/06/2026), pero no dice si el Desembolso 2 se libera con la primera parte o solo con ambas. Este libro asume ambas. | E7: ¿El Desembolso 2 se tramita con la Parte I o con el Producto 2 completo? | F7: Pendiente
B8: 4 | C8: Fecha de firma del convenio | D8: El convenio indica 16/10/2025. La Adenda dice en el punto 1.4 que se firmó el 14/11/2025 y en 1.2 que corre desde el 22/10/2025; pero en 2.1 cuenta desde el 16/10/2025, y sus fechas de la tabla 1 solo cuadran así. | E8: Confirmar por escrito que la fecha de inicio es el 16/10/2025. | F8: Pendiente
B9: 5 | C9: Monto de S/ 471,250 y de S/ 511,250 | D9: CARE recibe en efectivo S/ 471,250.00 (cl. 9.1). El tope de Profonanpe es S/ 511,250.00 (cl. 5.2.1). La diferencia de S/ 40,000.00 sería la compra directa de la UGP. | E9: ¿Profonanpe confirma que son S/ 471,250 más S/ 40,000 de compra directa? | F9: Pendiente
B10: 6 | C10: Estado real de las entregas y conformidades | D10: Los documentos solo prueban que el Producto 1 se presentó el 30/11/2025. No consta su conformidad ni el pago del 1.er desembolso. | E10: Registrar en Entregables y Desembolsos lo que ya ocurrió. | F10: Pendiente
B11: 7 | C11: Plazo de Profonanpe para transferir | D11: El convenio no fija en cuántos días transfiere Profonanpe una vez pedido el desembolso; además está sujeto a disponibilidad de fondos (cl. 9.5). | E11: ¿Cuál es el plazo referencial de transferencia? | F11: Pendiente

Sheet Parámetros
B1: ← Volver al Panel
B2: Parámetros y listas
B3: Datos base del convenio. Las celdas amarillas se pueden ajustar; todo el libro se recalcula.
B4: Parámetro | C4: Valor | D4: Fuente / nota | F4: Filtro de productos | H4: Sí / No | J4: Aviso (días) | L4: Estado de dudas | N4: Revisión UGP / FAO
B5: Fecha de inicio del convenio | C5: 45946 | D5: Cláusula 4.1 (modificada por la Adenda N.° 01, numeral 2.1): contado desde el 16/10/2025. | F5: Todos | H5: Sí | J5: 15 | L5: Pendiente | N5: En revisión
B6: Días hasta el cierre | C6: 589 | D6: Adenda N.° 01, numeral 2.3: 19 meses y 19 días (589 días). Cierre: 28/05/2027. | F6: Por entregar | H6: No | J6: 30 | L6: En consulta | N6: Observado
B7: Fecha de cierre | C7: =C5+C6 -> 46535 | D7: Calculado: inicio + días de cierre. | F7: Por vencer | J7: 45 | L7: Resuelta | N7: Conforme
B8: Monto en efectivo a CARE (S/) | C8: =SUM(Desembolsos!$B$5:$B$8) -> 471250 | D8: Cláusula 9.1: S/ 471,250.00 en 4 desembolsos. La Adenda (2.5) no cambia el monto. | F8: Vencido | J8: 60
B9: Compra directa de la UGP (S/) | C9: 40000 | D9: Cláusula 9.1: insumos, herramientas y equipos; no se descuentan del convenio. | F9: En revisión | J9: 90
B10: Tope total de Profonanpe (S/) | C10: =C8+C9 -> 511250 | D10: Cláusula 5.2.1: hasta S/ 511,250.00. | F10: Observado
B11: Rendición mínima del desembolso previo | C11: 0.7 | D11: Cláusula 9.1: al menos 70 % del desembolso anterior. | F11: Aprobado
B12: Días del fin original del convenio | C12: 540 | D12: Convenio original: 18 meses, hasta el 09/04/2027.
B13: Días para subsanar observaciones | C13: 7 | D13: Cláusula 8.1: 7 días calendario (ampliables 5 días con pedido escrito).
B14: Días de ampliación para subsanar | C14: 5 | D14: Cláusula 8.1: ampliación máxima con sustento escrito.
B15: Días para rendir el saldo del 4.º desembolso | C15: 10 | D15: Cláusula 9.2: a más tardar 10 días después del informe final.
B18: Cómo usar este libro
B19: 1. Panel: elige la fecha de referencia (vacía = hoy), los días de aviso, el filtro de la tabla y el producto a consultar.
B20: 2. Haz clic en los botones de color del Panel (Por vencer, Vencidos, Listos para solicitar…) para abrir la lista de ese estado en la hoja Vistas.
B21: 3. Entregables: cuando se presente un producto, marca «Sí» (columna L) y la fecha (M). Luego registra la revisión de la UGP/FAO (N a Q).
B22: 4. Desembolsos: marca «Sí» cuando Profonanpe transfiera (columna O), la fecha (P) y lo que CARE va rindiendo (Q).
B23: 5. Dudas: registra el estado y la respuesta de cada consulta a Profonanpe.
B24: Celdas amarillas con texto azul = datos que puedes editar. Lo demás son fórmulas: no las sobrescribas.

Sheet Datos gráficos
B2: Datos para gráficos y cálculos del Panel
B3: Hoja auxiliar: todo son fórmulas. No editar.
B4: Producto | C4: Inicio | D4: Por entregar | E4: Por vencer | F4: Vencido | G4: En revisión | H4: Observado | I4: Aprobado | J4: Cierre
B5: =Entregables!D5 -> Producto 1 | C5: =Entregables!G5 -> 45946 | D5: =IF(Entregables!S5="Por entregar",Entregables!H5-Entregables!G5+1,0) -> 0 | E5: =IF(Entregables!S5="Por vencer",Entregables!H5-Entregables!G5+1,0) -> 0 | F5: =IF(Entregables!S5="Vencido",Entregables!H5-Entregables!G5+1,0) -> 0 | G5: =IF(Entregables!S5="En revisión",Entregables!H5-Entregables!G5+1,0) -> 66 | H5: =IF(Entregables!S5="Observado",Entregables!H5-Entregables!G5+1,0) -> 0 | I5: =IF(Entregables!S5="Aprobado",Entregables!H5-Entregables!G5+1,0) -> 0 | J5: 0
B6: =Entregables!D6 -> Producto 2 · Parte I | C6: =Entregables!G6 -> 46012 | D6: =IF(Entregables!S6="Por entregar",Entregables!H6-Entregables!G6+1,0) -> 0 | E6: =IF(Entregables!S6="Por vencer",Entregables!H6-Entregables!G6+1,0) -> 0 | F6: =IF(Entregables!S6="Vencido",Entregables!H6-Entregables!G6+1,0) -> 131 | G6: =IF(Entregables!S6="En revisión",Entregables!H6-Entregables!G6+1,0) -> 0 | H6: =IF(Entregables!S6="Observado",Entregables!H6-Entregables!G6+1,0) -> 0 | I6: =IF(Entregables!S6="Aprobado",Entregables!H6-Entregables!G6+1,0) -> 0 | J6: 0
B7: =Entregables!D7 -> Producto 2 · Parte II | C7: =Entregables!G7 -> 46143 | D7: =IF(Entregables!S7="Por entregar",Entregables!H7-Entregables!G7+1,0) -> 0 | E7: =IF(Entregables!S7="Por vencer",Entregables!H7-Entregables!G7+1,0) -> 0 | F7: =IF(Entregables!S7="Vencido",Entregables!H7-Entregables!G7+1,0) -> 61 | G7: =IF(Entregables!S7="En revisión",Entregables!H7-Entregables!G7+1,0) -> 0 | H7: =IF(Entregables!S7="Observado",Entregables!H7-Entregables!G7+1,0) -> 0 | I7: =IF(Entregables!S7="Aprobado",Entregables!H7-Entregables!G7+1,0) -> 0 | J7: 0
B8: =Entregables!D8 -> Producto 3 | C8: =Entregables!G8 -> 46204 | D8: =IF(Entregables!S8="Por entregar",Entregables!H8-Entregables!G8+1,0) -> 171 | E8: =IF(Entregables!S8="Por vencer",Entregables!H8-Entregables!G8+1,0) -> 0 | F8: =IF(Entregables!S8="Vencido",Entregables!H8-Entregables!G8+1,0) -> 0 | G8: =IF(Entregables!S8="En revisión",Entregables!H8-Entregables!G8+1,0) -> 0 | H8: =IF(Entregables!S8="Observado",Entregables!H8-Entregables!G8+1,0) -> 0 | I8: =IF(Entregables!S8="Aprobado",Entregables!H8-Entregables!G8+1,0) -> 0 | J8: 0
B9: =Entregables!D9 -> Producto 4 | C9: =Entregables!G9 -> 46375 | D9: =IF(Entregables!S9="Por entregar",Entregables!H9-Entregables!G9+1,0) -> 133 | E9: =IF(Entregables!S9="Por vencer",Entregables!H9-Entregables!G9+1,0) -> 0 | F9: =IF(Entregables!S9="Vencido",Entregables!H9-Entregables!G9+1,0) -> 0 | G9: =IF(Entregables!S9="En revisión",Entregables!H9-Entregables!G9+1,0) -> 0 | H9: =IF(Entregables!S9="Observado",Entregables!H9-Entregables!G9+1,0) -> 0 | I9: =IF(Entregables!S9="Aprobado",Entregables!H9-Entregables!G9+1,0) -> 0 | J9: 0
B10: Cierre del convenio | C10: =Entregables!H9+1 -> 46508 | D10: 0 | E10: 0 | F10: 0 | G10: 0 | H10: 0 | I10: 0 | J10: =Cierre-C10+1 -> 28
B13: Estado del dinero | C13: Monto (S/)
B14: Desembolsado | C14: =Desembolsos!V9 -> 0
B15: Listo para solicitar | C15: =Desembolsos!W9 -> 0
B16: Falta rendición | C16: =Desembolsos!X9 -> 0
B17: En conformidad | C17: =Desembolsos!Y9 -> 141375
B18: Pendiente de producto | C18: =Desembolsos!Z9 -> 329875
B20: Desembolso | C20: Desembolsado | D20: Listo para solicitar | E20: Falta rendición | F20: En conformidad | G20: Pendiente de producto
B21: =Desembolsos!A5&" · "&TEXT(Desembolsos!C5*100,"0")&" %" -> D1 · 30 % | C21: =Desembolsos!V5 -> 0 | D21: =Desembolsos!W5 -> 0 | E21: =Desembolsos!X5 -> 0 | F21: =Desembolsos!Y5 -> 141375 | G21: =Desembolsos!Z5 -> 0
B22: =Desembolsos!A6&" · "&TEXT(Desembolsos!C6*100,"0")&" %" -> D2 · 30 % | C22: =Desembolsos!V6 -> 0 | D22: =Desembolsos!W6 -> 0 | E22: =Desembolsos!X6 -> 0 | F22: =Desembolsos!Y6 -> 0 | G22: =Desembolsos!Z6 -> 141375
B23: =Desembolsos!A7&" · "&TEXT(Desembolsos!C7*100,"0")&" %" -> D3 · 25 % | C23: =Desembolsos!V7 -> 0 | D23: =Desembolsos!W7 -> 0 | E23: =Desembolsos!X7 -> 0 | F23: =Desembolsos!Y7 -> 0 | G23: =Desembolsos!Z7 -> 117812
B24: =Desembolsos!A8&" · "&TEXT(Desembolsos!C8*100,"0")&" %" -> D4 · 15 % | C24: =Desembolsos!V8 -> 0 | D24: =Desembolsos!W8 -> 0 | E24: =Desembolsos!X8 -> 0 | F24: =Desembolsos!Y8 -> 0 | G24: =Desembolsos!Z8 -> 70688
B26: Estado del producto | C26: Cantidad
B27: Por entregar | C27: =COUNTIF(Entregables!$S$5:$S$9,"Por entregar") -> 2
B28: Por vencer | C28: =COUNTIF(Entregables!$S$5:$S$9,"Por vencer") -> 0
B29: Vencido | C29: =COUNTIF(Entregables!$S$5:$S$9,"Vencido") -> 2
B30: En revisión | C30: =COUNTIF(Entregables!$S$5:$S$9,"En revisión") -> 1
B31: Observado | C31: =COUNTIF(Entregables!$S$5:$S$9,"Observado") -> 0
B32: Aprobado | C32: =COUNTIF(Entregables!$S$5:$S$9,"Aprobado") -> 0
B34: Estado del desembolso | C34: Cantidad
B35: Desembolsado | C35: =COUNTIF(Desembolsos!$T$5:$T$8,"Desembolsado") -> 0
B36: Listo para solicitar | C36: =COUNTIF(Desembolsos!$T$5:$T$8,"Listo para solicitar") -> 0
B37: Falta rendición | C37: =COUNTIF(Desembolsos!$T$5:$T$8,"Falta rendición") -> 0
B38: En conformidad | C38: =COUNTIF(Desembolsos!$T$5:$T$8,"En conformidad") -> 1
B39: Pendiente de producto | C39: =COUNTIF(Desembolsos!$T$5:$T$8,"Pendiente de producto") -> 3
B41: Indicador | C41: Valor
B42: Próximo vencimiento (fecha) | C42: =_xlfn.MINIFS(Entregables!$H$5:$H$9,Entregables!$L$5:$L$9,"<>Sí",Entregables!$H$5:$H$9,">="&FechaRef) -> 46374
B43: Próximo vencimiento (producto) | C43: =IF('Datos gráficos'!$C$42=0,"",INDEX(Entregables!$D$5:$D$9,MATCH('Datos gráficos'!$C$42,Entregables!$H$5:$H$9,0))) -> Producto 3
B44: Días al próximo vencimiento | C44: =IF('Datos gráficos'!$C$42=0,"",'Datos gráficos'!$C$42-FechaRef) -> 65
B45: Productos vencidos | C45: =COUNTIF(Entregables!$S$5:$S$9,"Vencido") -> 2
B46: Productos por vencer | C46: =COUNTIF(Entregables!$S$5:$S$9,"Por vencer") -> 0
B47: Productos entregados | C47: =COUNTIF(Entregables!$L$5:$L$9,"Sí") -> 1
B48: Productos aprobados | C48: =COUNTIF(Entregables!$S$5:$S$9,"Aprobado") -> 0
B49: Avance físico (entregado, % Adenda) | C49: =SUMIF(Entregables!$L$5:$L$9,"Sí",Entregables!$J$5:$J$9) -> 0.3
B50: Ejecución financiera | C50: =IF(TotalCARE=0,0,Desembolsos!V9/TotalCARE) -> 0
B51: Rendido / desembolsado | C51: =IF(Desembolsos!V9=0,0,MIN(1,SUMIF(Desembolsos!$O$5:$O$8,"Sí",Desembolsos!$Q$5:$Q$8)/Desembolsos!V9)) -> 0
B52: Tiempo transcurrido | C52: =MAX(0,MIN(1,(FechaRef-Inicio)/DiasConvenio)) -> 0.61629881
B53: Días al cierre | C53: =Cierre-FechaRef -> 226
B54: Dudas pendientes | C54: =COUNTIF(Dudas!$F$5:$F$11,"<>Resuelta") -> 7
B55: Productos en el filtro | C55: =COUNTIF(Entregables!$AA$5:$AA$9,TRUE()) -> 5
B56: Fila del producto consultado | C56: =IFERROR(MATCH(ProdSel,Entregables!$D$5:$D$9,0),1) -> 4
B57: Saldo por rendir | C57: =Desembolsos!S9 -> 0
B58: Monto rendido | C58: =SUMIF(Desembolsos!$O$5:$O$8,"Sí",Desembolsos!$Q$5:$Q$8) -> 0
B59: Productos observados | C59: =COUNTIF(Entregables!$S$5:$S$9,"Observado") -> 0
